{"TeamOverall":{"GROUP_SET":"Overall","TEAM_ID":1610612759,"TEAM_NAME":"San Antonio Spurs","GROUP_VALUE":"2011-12","GP":14,"W":10,"L":4,"W_PCT":0.714,"MIN":672,"E_OFF_RATING":107.9,"OFF_RATING":109.3,"E_DEF_RATING":101.6,"DEF_RATING":102.8,"E_NET_RATING":6.3,"NET_RATING":6.5,"AST_PCT":0.603,"AST_TO":1.6,"AST_RATIO":18,"OREB_PCT":0.249,"DREB_PCT":0.717,"REB_PCT":0.493,"TM_TOV_PCT":0.153,"EFG_PCT":0.541,"TS_PCT":0.574,"E_PACE":94.6,"PACE":93.36,"PACE_PER40":77.8,"POSS":1306,"PIE":0.529,"GP_RANK":1,"W_RANK":1,"L_RANK":1,"W_PCT_RANK":1,"MIN_RANK":1,"OFF_RATING_RANK":1,"DEF_RATING_RANK":1,"NET_RATING_RANK":1,"AST_PCT_RANK":1,"AST_TO_RANK":1,"AST_RATIO_RANK":1,"OREB_PCT_RANK":1,"DREB_PCT_RANK":1,"REB_PCT_RANK":1,"TM_TOV_PCT_RANK":1,"EFG_PCT_RANK":1,"TS_PCT_RANK":1,"PACE_RANK":1,"PIE_RANK":1},"PlayersSeasonTotals":{"0":{"GROUP_SET":"Players","PLAYER_ID":2564,"PLAYER_NAME":"Boris Diaw","GP":14,"W":10,"L":4,"W_PCT":0.714,"MIN":24.7,"E_OFF_RATING":108,"OFF_RATING":108.9,"sp_work_OFF_RATING":108.9,"E_DEF_RATING":94,"DEF_RATING":94.1,"sp_work_DEF_RATING":94.1,"E_NET_RATING":14,"NET_RATING":14.8,"sp_work_NET_RATING":14.8,"AST_PCT":0.14,"AST_TO":2.33,"AST_RATIO":28.5,"OREB_PCT":0.085,"DREB_PCT":0.128,"REB_PCT":0.107,"TM_TOV_PCT":12.2,"E_TOV_PCT":12.1,"EFG_PCT":0.579,"TS_PCT":0.592,"USG_PCT":0.116,"E_USG_PCT":0.118,"E_PACE":93.97,"PACE":93.52,"PACE_PER40":77.93,"sp_work_PACE":93.52,"PIE":0.094,"POSS":674,"FGM":36,"FGA":70,"FGM_PG":2.6,"FGA_PG":5,"FG_PCT":0.514,"GP_RANK":1,"W_RANK":1,"L_RANK":4,"W_PCT_RANK":4,"MIN_RANK":5,"E_OFF_RATING_RANK":7,"OFF_RATING_RANK":5,"sp_work_OFF_RATING_RANK":5,"E_DEF_RATING_RANK":2,"DEF_RATING_RANK":2,"sp_work_DEF_RATING_RANK":2,"E_NET_RATING_RANK":2,"NET_RATING_RANK":3,"sp_work_NET_RATING_RANK":3,"AST_PCT_RANK":6,"AST_TO_RANK":2,"AST_RATIO_RANK":1,"OREB_PCT_RANK":2,"DREB_PCT_RANK":7,"REB_PCT_RANK":5,"TM_TOV_PCT_RANK":10,"E_TOV_PCT_RANK":10,"EFG_PCT_RANK":6,"TS_PCT_RANK":7,"USG_PCT_RANK":12,"E_USG_PCT_RANK":12,"E_PACE_RANK":7,"PACE_RANK":8,"sp_work_PACE_RANK":8,"PIE_RANK":8,"FGM_RANK":8,"FGA_RANK":8,"FGM_PG_RANK":8,"FGA_PG_RANK":8,"FG_PCT_RANK":5},"1":{"GROUP_SET":"Players","PLAYER_ID":201980,"PLAYER_NAME":"Danny Green","GP":14,"W":10,"L":4,"W_PCT":0.714,"MIN":20.7,"E_OFF_RATING":112.9,"OFF_RATING":113.2,"sp_work_OFF_RATING":113.2,"E_DEF_RATING":93.2,"DEF_RATING":93.1,"sp_work_DEF_RATING":93.1,"E_NET_RATING":19.7,"NET_RATING":20.1,"sp_work_NET_RATING":20.1,"AST_PCT":0.073,"AST_TO":1,"AST_RATIO":11.9,"OREB_PCT":0.012,"DREB_PCT":0.139,"REB_PCT":0.081,"TM_TOV_PCT":11.9,"E_TOV_PCT":12,"EFG_PCT":0.527,"TS_PCT":0.54,"USG_PCT":0.182,"E_USG_PCT":0.184,"E_PACE":91.7,"PACE":91.64,"PACE_PER40":76.37,"sp_work_PACE":91.64,"PIE":0.076,"POSS":552,"FGM":38,"FGA":91,"FGM_PG":2.7,"FGA_PG":6.5,"FG_PCT":0.418,"GP_RANK":1,"W_RANK":1,"L_RANK":4,"W_PCT_RANK":4,"MIN_RANK":7,"E_OFF_RATING_RANK":3,"OFF_RATING_RANK":1,"sp_work_OFF_RATING_RANK":1,"E_DEF_RATING_RANK":1,"DEF_RATING_RANK":1,"sp_work_DEF_RATING_RANK":1,"E_NET_RATING_RANK":1,"NET_RATING_RANK":1,"sp_work_NET_RATING_RANK":1,"AST_PCT_RANK":11,"AST_TO_RANK":11,"AST_RATIO_RANK":10,"OREB_PCT_RANK":11,"DREB_PCT_RANK":6,"REB_PCT_RANK":7,"TM_TOV_PCT_RANK":9,"E_TOV_PCT_RANK":9,"EFG_PCT_RANK":10,"TS_PCT_RANK":10,"USG_PCT_RANK":8,"E_USG_PCT_RANK":8,"E_PACE_RANK":11,"PACE_RANK":12,"sp_work_PACE_RANK":12,"PIE_RANK":12,"FGM_RANK":6,"FGA_RANK":4,"FGM_PG_RANK":6,"FGA_PG_RANK":4,"FG_PCT_RANK":12},"2":{"GROUP_SET":"Players","PLAYER_ID":201971,"PLAYER_NAME":"DeJuan Blair","GP":10,"W":6,"L":4,"W_PCT":0.6,"MIN":7.6,"E_OFF_RATING":105.6,"OFF_RATING":103.4,"sp_work_OFF_RATING":103.4,"E_DEF_RATING":112.1,"DEF_RATING":111.6,"sp_work_DEF_RATING":111.6,"E_NET_RATING":-6.4,"NET_RATING":-8.2,"sp_work_NET_RATING":-8.2,"AST_PCT":0.043,"AST_TO":2,"AST_RATIO":6.1,"OREB_PCT":0.099,"DREB_PCT":0.219,"REB_PCT":0.16,"TM_TOV_PCT":3,"E_TOV_PCT":3.1,"EFG_PCT":0.63,"TS_PCT":0.624,"USG_PCT":0.187,"E_USG_PCT":0.193,"E_PACE":92.28,"PACE":93.49,"PACE_PER40":77.91,"sp_work_PACE":93.49,"PIE":0.138,"POSS":149,"FGM":17,"FGA":27,"FGM_PG":1.7,"FGA_PG":2.7,"FG_PCT":0.63,"GP_RANK":11,"W_RANK":12,"L_RANK":4,"W_PCT_RANK":13,"MIN_RANK":11,"E_OFF_RATING_RANK":11,"OFF_RATING_RANK":11,"sp_work_OFF_RATING_RANK":11,"E_DEF_RATING_RANK":10,"DEF_RATING_RANK":11,"sp_work_DEF_RATING_RANK":11,"E_NET_RATING_RANK":12,"NET_RATING_RANK":10,"sp_work_NET_RATING_RANK":10,"AST_PCT_RANK":12,"AST_TO_RANK":4,"AST_RATIO_RANK":13,"OREB_PCT_RANK":1,"DREB_PCT_RANK":1,"REB_PCT_RANK":1,"TM_TOV_PCT_RANK":2,"E_TOV_PCT_RANK":2,"EFG_PCT_RANK":4,"TS_PCT_RANK":3,"USG_PCT_RANK":7,"E_USG_PCT_RANK":7,"E_PACE_RANK":10,"PACE_RANK":9,"sp_work_PACE_RANK":9,"PIE_RANK":2,"FGM_RANK":10,"FGA_RANK":11,"FGM_PG_RANK":10,"FGA_PG_RANK":10,"FG_PCT_RANK":2},"3":{"GROUP_SET":"Players","PLAYER_ID":202390,"PLAYER_NAME":"Gary Neal","GP":14,"W":10,"L":4,"W_PCT":0.714,"MIN":15.5,"E_OFF_RATING":102.5,"OFF_RATING":101.4,"sp_work_OFF_RATING":101.4,"E_DEF_RATING":113.4,"DEF_RATING":110.6,"sp_work_DEF_RATING":110.6,"E_NET_RATING":-11,"NET_RATING":-9.2,"sp_work_NET_RATING":-9.2,"AST_PCT":0.16,"AST_TO":1.73,"AST_RATIO":16.2,"OREB_PCT":0.005,"DREB_PCT":0.082,"REB_PCT":0.043,"TM_TOV_PCT":9.4,"E_TOV_PCT":9.3,"EFG_PCT":0.573,"TS_PCT":0.598,"USG_PCT":0.205,"E_USG_PCT":0.213,"E_PACE":95.79,"PACE":97.54,"PACE_PER40":81.28,"sp_work_PACE":97.54,"PIE":0.092,"POSS":437,"FGM":39,"FGA":82,"FGM_PG":2.8,"FGA_PG":5.9,"FG_PCT":0.476,"GP_RANK":1,"W_RANK":1,"L_RANK":4,"W_PCT_RANK":4,"MIN_RANK":8,"E_OFF_RATING_RANK":12,"OFF_RATING_RANK":12,"sp_work_OFF_RATING_RANK":12,"E_DEF_RATING_RANK":11,"DEF_RATING_RANK":9,"sp_work_DEF_RATING_RANK":9,"E_NET_RATING_RANK":13,"NET_RATING_RANK":11,"sp_work_NET_RATING_RANK":11,"AST_PCT_RANK":4,"AST_TO_RANK":6,"AST_RATIO_RANK":8,"OREB_PCT_RANK":12,"DREB_PCT_RANK":11,"REB_PCT_RANK":13,"TM_TOV_PCT_RANK":5,"E_TOV_PCT_RANK":5,"EFG_PCT_RANK":7,"TS_PCT_RANK":5,"USG_PCT_RANK":5,"E_USG_PCT_RANK":4,"E_PACE_RANK":5,"PACE_RANK":3,"sp_work_PACE_RANK":3,"PIE_RANK":9,"FGM_RANK":5,"FGA_RANK":6,"FGM_PG_RANK":5,"FGA_PG_RANK":6,"FG_PCT_RANK":8},"4":{"GROUP_SET":"Players","PLAYER_ID":202341,"PLAYER_NAME":"James Anderson","GP":8,"W":7,"L":1,"W_PCT":0.875,"MIN":3.9,"E_OFF_RATING":124.6,"OFF_RATING":111.7,"sp_work_OFF_RATING":111.7,"E_DEF_RATING":121.6,"DEF_RATING":125.9,"sp_work_DEF_RATING":125.9,"E_NET_RATING":3,"NET_RATING":-14.2,"sp_work_NET_RATING":-14.2,"AST_PCT":0.125,"AST_TO":0,"AST_RATIO":23.1,"OREB_PCT":0,"DREB_PCT":0.167,"REB_PCT":0.085,"TM_TOV_PCT":0,"E_TOV_PCT":0,"EFG_PCT":0.556,"TS_PCT":0.557,"USG_PCT":0.141,"E_USG_PCT":0.157,"E_PACE":87.47,"PACE":90.7,"PACE_PER40":75.58,"sp_work_PACE":90.7,"PIE":0.097,"POSS":60,"FGM":4,"FGA":9,"FGM_PG":0.5,"FGA_PG":1.1,"FG_PCT":0.444,"GP_RANK":12,"W_RANK":11,"L_RANK":1,"W_PCT_RANK":1,"MIN_RANK":12,"E_OFF_RATING_RANK":1,"OFF_RATING_RANK":2,"sp_work_OFF_RATING_RANK":2,"E_DEF_RATING_RANK":13,"DEF_RATING_RANK":13,"sp_work_DEF_RATING_RANK":13,"E_NET_RATING_RANK":6,"NET_RATING_RANK":12,"sp_work_NET_RATING_RANK":12,"AST_PCT_RANK":7,"AST_TO_RANK":13,"AST_RATIO_RANK":4,"OREB_PCT_RANK":13,"DREB_PCT_RANK":4,"REB_PCT_RANK":6,"TM_TOV_PCT_RANK":1,"E_TOV_PCT_RANK":1,"EFG_PCT_RANK":8,"TS_PCT_RANK":9,"USG_PCT_RANK":10,"E_USG_PCT_RANK":9,"E_PACE_RANK":13,"PACE_RANK":13,"sp_work_PACE_RANK":13,"PIE_RANK":7,"FGM_RANK":13,"FGA_RANK":13,"FGM_PG_RANK":13,"FGA_PG_RANK":13,"FG_PCT_RANK":11},"5":{"GROUP_SET":"Players","PLAYER_ID":202695,"PLAYER_NAME":"Kawhi Leonard","GP":14,"W":10,"L":4,"W_PCT":0.714,"MIN":27.1,"E_OFF_RATING":105.9,"OFF_RATING":106.5,"sp_work_OFF_RATING":106.5,"E_DEF_RATING":101.1,"DEF_RATING":101.1,"sp_work_DEF_RATING":101.1,"E_NET_RATING":4.8,"NET_RATING":5.4,"sp_work_NET_RATING":5.4,"AST_PCT":0.031,"AST_TO":0.62,"AST_RATIO":6.8,"OREB_PCT":0.05,"DREB_PCT":0.178,"REB_PCT":0.114,"TM_TOV_PCT":11.1,"E_TOV_PCT":11,"EFG_PCT":0.6,"TS_PCT":0.623,"USG_PCT":0.13,"E_USG_PCT":0.134,"E_PACE":94.55,"PACE":94.32,"PACE_PER40":78.6,"sp_work_PACE":94.32,"PIE":0.104,"POSS":741,"FGM":45,"FGA":90,"FGM_PG":3.2,"FGA_PG":6.4,"FG_PCT":0.5,"GP_RANK":1,"W_RANK":1,"L_RANK":4,"W_PCT_RANK":4,"MIN_RANK":4,"E_OFF_RATING_RANK":9,"OFF_RATING_RANK":7,"sp_work_OFF_RATING_RANK":7,"E_DEF_RATING_RANK":5,"DEF_RATING_RANK":5,"sp_work_DEF_RATING_RANK":5,"E_NET_RATING_RANK":5,"NET_RATING_RANK":5,"sp_work_NET_RATING_RANK":5,"AST_PCT_RANK":13,"AST_TO_RANK":12,"AST_RATIO_RANK":12,"OREB_PCT_RANK":5,"DREB_PCT_RANK":3,"REB_PCT_RANK":3,"TM_TOV_PCT_RANK":8,"E_TOV_PCT_RANK":8,"EFG_PCT_RANK":5,"TS_PCT_RANK":4,"USG_PCT_RANK":11,"E_USG_PCT_RANK":11,"E_PACE_RANK":6,"PACE_RANK":7,"sp_work_PACE_RANK":7,"PIE_RANK":5,"FGM_RANK":4,"FGA_RANK":5,"FGM_PG_RANK":4,"FGA_PG_RANK":5,"FG_PCT_RANK":6},"6":{"GROUP_SET":"Players","PLAYER_ID":1938,"PLAYER_NAME":"Manu Ginobili","GP":14,"W":10,"L":4,"W_PCT":0.714,"MIN":27.9,"E_OFF_RATING":105.6,"OFF_RATING":105.7,"sp_work_OFF_RATING":105.7,"E_DEF_RATING":103.4,"DEF_RATING":102.4,"sp_work_DEF_RATING":102.4,"E_NET_RATING":2.2,"NET_RATING":3.3,"sp_work_NET_RATING":3.3,"AST_PCT":0.247,"AST_TO":1.33,"AST_RATIO":21.1,"OREB_PCT":0.022,"DREB_PCT":0.101,"REB_PCT":0.064,"TM_TOV_PCT":15.8,"E_TOV_PCT":15.7,"EFG_PCT":0.528,"TS_PCT":0.592,"USG_PCT":0.238,"E_USG_PCT":0.245,"E_PACE":96.89,"PACE":97.35,"PACE_PER40":81.12,"sp_work_PACE":97.35,"PIE":0.114,"POSS":791,"FGM":65,"FGA":145,"FGM_PG":4.6,"FGA_PG":10.4,"FG_PCT":0.448,"GP_RANK":1,"W_RANK":1,"L_RANK":4,"W_PCT_RANK":4,"MIN_RANK":3,"E_OFF_RATING_RANK":10,"OFF_RATING_RANK":8,"sp_work_OFF_RATING_RANK":8,"E_DEF_RATING_RANK":6,"DEF_RATING_RANK":6,"sp_work_DEF_RATING_RANK":6,"E_NET_RATING_RANK":7,"NET_RATING_RANK":6,"sp_work_NET_RATING_RANK":6,"AST_PCT_RANK":2,"AST_TO_RANK":8,"AST_RATIO_RANK":5,"OREB_PCT_RANK":7,"DREB_PCT_RANK":9,"REB_PCT_RANK":9,"TM_TOV_PCT_RANK":13,"E_TOV_PCT_RANK":12,"EFG_PCT_RANK":9,"TS_PCT_RANK":6,"USG_PCT_RANK":3,"E_USG_PCT_RANK":3,"E_PACE_RANK":2,"PACE_RANK":4,"sp_work_PACE_RANK":4,"PIE_RANK":4,"FGM_RANK":3,"FGA_RANK":3,"FGM_PG_RANK":3,"FGA_PG_RANK":3,"FG_PCT_RANK":10},"7":{"GROUP_SET":"Players","PLAYER_ID":2588,"PLAYER_NAME":"Matt Bonner","GP":13,"W":10,"L":3,"W_PCT":0.769,"MIN":12.7,"E_OFF_RATING":101.2,"OFF_RATING":100.6,"sp_work_OFF_RATING":100.6,"E_DEF_RATING":104.7,"DEF_RATING":103.8,"sp_work_DEF_RATING":103.8,"E_NET_RATING":-3.5,"NET_RATING":-3.2,"sp_work_NET_RATING":-3.2,"AST_PCT":0.083,"AST_TO":3,"AST_RATIO":19.6,"OREB_PCT":0.013,"DREB_PCT":0.124,"REB_PCT":0.074,"TM_TOV_PCT":6.5,"E_TOV_PCT":6.5,"EFG_PCT":0.438,"TS_PCT":0.453,"USG_PCT":0.101,"E_USG_PCT":0.104,"E_PACE":97.25,"PACE":97.94,"PACE_PER40":81.61,"sp_work_PACE":97.94,"PIE":0.032,"POSS":335,"FGM":10,"FGA":32,"FGM_PG":0.8,"FGA_PG":2.5,"FG_PCT":0.313,"GP_RANK":9,"W_RANK":1,"L_RANK":3,"W_PCT_RANK":2,"MIN_RANK":10,"E_OFF_RATING_RANK":13,"OFF_RATING_RANK":13,"sp_work_OFF_RATING_RANK":13,"E_DEF_RATING_RANK":7,"DEF_RATING_RANK":7,"sp_work_DEF_RATING_RANK":7,"E_NET_RATING_RANK":10,"NET_RATING_RANK":8,"sp_work_NET_RATING_RANK":8,"AST_PCT_RANK":10,"AST_TO_RANK":1,"AST_RATIO_RANK":7,"OREB_PCT_RANK":10,"DREB_PCT_RANK":8,"REB_PCT_RANK":8,"TM_TOV_PCT_RANK":3,"E_TOV_PCT_RANK":3,"EFG_PCT_RANK":13,"TS_PCT_RANK":13,"USG_PCT_RANK":13,"E_USG_PCT_RANK":13,"E_PACE_RANK":1,"PACE_RANK":1,"sp_work_PACE_RANK":1,"PIE_RANK":13,"FGM_RANK":11,"FGA_RANK":10,"FGM_PG_RANK":11,"FGA_PG_RANK":11,"FG_PCT_RANK":13},"8":{"GROUP_SET":"Players","PLAYER_ID":201988,"PLAYER_NAME":"Patty Mills","GP":8,"W":6,"L":2,"W_PCT":0.75,"MIN":3.9,"E_OFF_RATING":115.8,"OFF_RATING":104.7,"sp_work_OFF_RATING":104.7,"E_DEF_RATING":118.3,"DEF_RATING":120.3,"sp_work_DEF_RATING":120.3,"E_NET_RATING":-2.5,"NET_RATING":-15.7,"sp_work_NET_RATING":-15.7,"AST_PCT":0.208,"AST_TO":1.67,"AST_RATIO":26.3,"OREB_PCT":0.036,"DREB_PCT":0.071,"REB_PCT":0.054,"TM_TOV_PCT":15.8,"E_TOV_PCT":15.8,"EFG_PCT":0.682,"TS_PCT":0.682,"USG_PCT":0.192,"E_USG_PCT":0.213,"E_PACE":91.63,"PACE":95.58,"PACE_PER40":79.65,"sp_work_PACE":95.58,"PIE":0.103,"POSS":64,"FGM":6,"FGA":11,"FGM_PG":0.8,"FGA_PG":1.4,"FG_PCT":0.545,"GP_RANK":12,"W_RANK":12,"L_RANK":2,"W_PCT_RANK":3,"MIN_RANK":13,"E_OFF_RATING_RANK":2,"OFF_RATING_RANK":10,"sp_work_OFF_RATING_RANK":10,"E_DEF_RATING_RANK":12,"DEF_RATING_RANK":12,"sp_work_DEF_RATING_RANK":12,"E_NET_RATING_RANK":9,"NET_RATING_RANK":13,"sp_work_NET_RATING_RANK":13,"AST_PCT_RANK":3,"AST_TO_RANK":7,"AST_RATIO_RANK":2,"OREB_PCT_RANK":6,"DREB_PCT_RANK":13,"REB_PCT_RANK":10,"TM_TOV_PCT_RANK":12,"E_TOV_PCT_RANK":13,"EFG_PCT_RANK":2,"TS_PCT_RANK":2,"USG_PCT_RANK":6,"E_USG_PCT_RANK":5,"E_PACE_RANK":12,"PACE_RANK":6,"sp_work_PACE_RANK":6,"PIE_RANK":6,"FGM_RANK":12,"FGA_RANK":12,"FGM_PG_RANK":12,"FGA_PG_RANK":12,"FG_PCT_RANK":3},"9":{"GROUP_SET":"Players","PLAYER_ID":1536,"PLAYER_NAME":"Stephen Jackson","GP":14,"W":10,"L":4,"W_PCT":0.714,"MIN":21.3,"E_OFF_RATING":109.4,"OFF_RATING":108.8,"sp_work_OFF_RATING":108.8,"E_DEF_RATING":108.4,"DEF_RATING":108.6,"sp_work_DEF_RATING":108.6,"E_NET_RATING":1,"NET_RATING":0.2,"sp_work_NET_RATING":0.2,"AST_PCT":0.122,"AST_TO":1.33,"AST_RATIO":20.2,"OREB_PCT":0.019,"DREB_PCT":0.076,"REB_PCT":0.05,"TM_TOV_PCT":15.1,"E_TOV_PCT":15.1,"EFG_PCT":0.718,"TS_PCT":0.747,"USG_PCT":0.145,"E_USG_PCT":0.149,"E_PACE":96.76,"PACE":96.93,"PACE_PER40":80.77,"sp_work_PACE":96.93,"PIE":0.082,"POSS":602,"FGM":38,"FGA":71,"FGM_PG":2.7,"FGA_PG":5.1,"FG_PCT":0.535,"GP_RANK":1,"W_RANK":1,"L_RANK":4,"W_PCT_RANK":4,"MIN_RANK":6,"E_OFF_RATING_RANK":5,"OFF_RATING_RANK":6,"sp_work_OFF_RATING_RANK":6,"E_DEF_RATING_RANK":8,"DEF_RATING_RANK":8,"sp_work_DEF_RATING_RANK":8,"E_NET_RATING_RANK":8,"NET_RATING_RANK":7,"sp_work_NET_RATING_RANK":7,"AST_PCT_RANK":8,"AST_TO_RANK":8,"AST_RATIO_RANK":6,"OREB_PCT_RANK":8,"DREB_PCT_RANK":12,"REB_PCT_RANK":12,"TM_TOV_PCT_RANK":11,"E_TOV_PCT_RANK":11,"EFG_PCT_RANK":1,"TS_PCT_RANK":1,"USG_PCT_RANK":9,"E_USG_PCT_RANK":10,"E_PACE_RANK":3,"PACE_RANK":5,"sp_work_PACE_RANK":5,"PIE_RANK":11,"FGM_RANK":6,"FGA_RANK":7,"FGM_PG_RANK":6,"FGA_PG_RANK":7,"FG_PCT_RANK":4},"10":{"GROUP_SET":"Players","PLAYER_ID":201168,"PLAYER_NAME":"Tiago Splitter","GP":13,"W":9,"L":4,"W_PCT":0.692,"MIN":12.9,"E_OFF_RATING":106.9,"OFF_RATING":104.7,"sp_work_OFF_RATING":104.7,"E_DEF_RATING":111.5,"DEF_RATING":110.8,"sp_work_DEF_RATING":110.8,"E_NET_RATING":-4.5,"NET_RATING":-6,"sp_work_NET_RATING":-6,"AST_PCT":0.108,"AST_TO":1.11,"AST_RATIO":11.8,"OREB_PCT":0.056,"DREB_PCT":0.161,"REB_PCT":0.114,"TM_TOV_PCT":10.6,"E_TOV_PCT":10.6,"EFG_PCT":0.638,"TS_PCT":0.576,"USG_PCT":0.206,"E_USG_PCT":0.212,"E_PACE":96.34,"PACE":97.65,"PACE_PER40":81.38,"sp_work_PACE":97.65,"PIE":0.082,"POSS":338,"FGM":30,"FGA":47,"FGM_PG":2.3,"FGA_PG":3.6,"FG_PCT":0.638,"GP_RANK":9,"W_RANK":10,"L_RANK":4,"W_PCT_RANK":12,"MIN_RANK":9,"E_OFF_RATING_RANK":8,"OFF_RATING_RANK":9,"sp_work_OFF_RATING_RANK":9,"E_DEF_RATING_RANK":9,"DEF_RATING_RANK":10,"sp_work_DEF_RATING_RANK":10,"E_NET_RATING_RANK":11,"NET_RATING_RANK":9,"sp_work_NET_RATING_RANK":9,"AST_PCT_RANK":9,"AST_TO_RANK":10,"AST_RATIO_RANK":11,"OREB_PCT_RANK":4,"DREB_PCT_RANK":5,"REB_PCT_RANK":4,"TM_TOV_PCT_RANK":6,"E_TOV_PCT_RANK":6,"EFG_PCT_RANK":3,"TS_PCT_RANK":8,"USG_PCT_RANK":4,"E_USG_PCT_RANK":6,"E_PACE_RANK":4,"PACE_RANK":2,"sp_work_PACE_RANK":2,"PIE_RANK":10,"FGM_RANK":9,"FGA_RANK":9,"FGM_PG_RANK":9,"FGA_PG_RANK":9,"FG_PCT_RANK":1},"11":{"GROUP_SET":"Players","PLAYER_ID":1495,"PLAYER_NAME":"Tim Duncan","GP":14,"W":10,"L":4,"W_PCT":0.714,"MIN":33.1,"E_OFF_RATING":109.9,"OFF_RATING":111.3,"sp_work_OFF_RATING":111.3,"E_DEF_RATING":96.1,"DEF_RATING":96.1,"sp_work_DEF_RATING":96.1,"E_NET_RATING":13.8,"NET_RATING":15.2,"sp_work_NET_RATING":15.2,"AST_PCT":0.143,"AST_TO":1.86,"AST_RATIO":13.5,"OREB_PCT":0.074,"DREB_PCT":0.217,"REB_PCT":0.148,"TM_TOV_PCT":7.3,"E_TOV_PCT":7.3,"EFG_PCT":0.495,"TS_PCT":0.529,"USG_PCT":0.249,"E_USG_PCT":0.251,"E_PACE":93.33,"PACE":92.74,"PACE_PER40":77.29,"sp_work_PACE":92.74,"PIE":0.156,"POSS":895,"FGM":101,"FGA":204,"FGM_PG":7.2,"FGA_PG":14.6,"FG_PCT":0.495,"GP_RANK":1,"W_RANK":1,"L_RANK":4,"W_PCT_RANK":4,"MIN_RANK":2,"E_OFF_RATING_RANK":4,"OFF_RATING_RANK":3,"sp_work_OFF_RATING_RANK":3,"E_DEF_RATING_RANK":3,"DEF_RATING_RANK":3,"sp_work_DEF_RATING_RANK":3,"E_NET_RATING_RANK":3,"NET_RATING_RANK":2,"sp_work_NET_RATING_RANK":2,"AST_PCT_RANK":5,"AST_TO_RANK":5,"AST_RATIO_RANK":9,"OREB_PCT_RANK":3,"DREB_PCT_RANK":2,"REB_PCT_RANK":2,"TM_TOV_PCT_RANK":4,"E_TOV_PCT_RANK":4,"EFG_PCT_RANK":11,"TS_PCT_RANK":12,"USG_PCT_RANK":2,"E_USG_PCT_RANK":2,"E_PACE_RANK":9,"PACE_RANK":11,"sp_work_PACE_RANK":11,"PIE_RANK":1,"FGM_RANK":2,"FGA_RANK":2,"FGM_PG_RANK":2,"FGA_PG_RANK":2,"FG_PCT_RANK":7},"12":{"GROUP_SET":"Players","PLAYER_ID":2225,"PLAYER_NAME":"Tony Parker","GP":14,"W":10,"L":4,"W_PCT":0.714,"MIN":36.1,"E_OFF_RATING":109.3,"OFF_RATING":110.6,"sp_work_OFF_RATING":110.6,"E_DEF_RATING":97.8,"DEF_RATING":98.4,"sp_work_DEF_RATING":98.4,"E_NET_RATING":11.5,"NET_RATING":12.3,"sp_work_NET_RATING":12.3,"AST_PCT":0.314,"AST_TO":2.16,"AST_RATIO":23.6,"OREB_PCT":0.017,"DREB_PCT":0.083,"REB_PCT":0.052,"TM_TOV_PCT":10.9,"E_TOV_PCT":10.9,"EFG_PCT":0.469,"TS_PCT":0.535,"USG_PCT":0.281,"E_USG_PCT":0.283,"E_PACE":93.58,"PACE":92.77,"PACE_PER40":77.31,"sp_work_PACE":92.77,"PIE":0.13,"POSS":979,"FGM":102,"FGA":225,"FGM_PG":7.3,"FGA_PG":16.1,"FG_PCT":0.453,"GP_RANK":1,"W_RANK":1,"L_RANK":4,"W_PCT_RANK":4,"MIN_RANK":1,"E_OFF_RATING_RANK":6,"OFF_RATING_RANK":4,"sp_work_OFF_RATING_RANK":4,"E_DEF_RATING_RANK":4,"DEF_RATING_RANK":4,"sp_work_DEF_RATING_RANK":4,"E_NET_RATING_RANK":4,"NET_RATING_RANK":4,"sp_work_NET_RATING_RANK":4,"AST_PCT_RANK":1,"AST_TO_RANK":3,"AST_RATIO_RANK":3,"OREB_PCT_RANK":9,"DREB_PCT_RANK":10,"REB_PCT_RANK":11,"TM_TOV_PCT_RANK":7,"E_TOV_PCT_RANK":7,"EFG_PCT_RANK":12,"TS_PCT_RANK":11,"USG_PCT_RANK":1,"E_USG_PCT_RANK":1,"E_PACE_RANK":8,"PACE_RANK":10,"sp_work_PACE_RANK":10,"PIE_RANK":3,"FGM_RANK":1,"FGA_RANK":1,"FGM_PG_RANK":1,"FGA_PG_RANK":1,"FG_PCT_RANK":9}}}