{"TeamOverall":{"GROUP_SET":"Overall","TEAM_ID":1610612742,"TEAM_NAME":"Dallas Mavericks","GROUP_VALUE":"2001-02","GP":8,"W":4,"L":4,"W_PCT":0.5,"MIN":389,"E_OFF_RATING":108.2,"OFF_RATING":110.1,"E_DEF_RATING":109.3,"DEF_RATING":110.3,"E_NET_RATING":-1.1,"NET_RATING":-0.2,"AST_PCT":0.494,"AST_TO":1.57,"AST_RATIO":14.9,"OREB_PCT":0.281,"DREB_PCT":0.656,"REB_PCT":0.469,"TM_TOV_PCT":0.126,"EFG_PCT":0.499,"TS_PCT":0.55,"E_PACE":98.8,"PACE":97.54,"PACE_PER40":81.29,"POSS":792,"PIE":0.488,"GP_RANK":1,"W_RANK":1,"L_RANK":1,"W_PCT_RANK":1,"MIN_RANK":1,"OFF_RATING_RANK":1,"DEF_RATING_RANK":1,"NET_RATING_RANK":1,"AST_PCT_RANK":1,"AST_TO_RANK":1,"AST_RATIO_RANK":1,"OREB_PCT_RANK":1,"DREB_PCT_RANK":1,"REB_PCT_RANK":1,"TM_TOV_PCT_RANK":1,"EFG_PCT_RANK":1,"TS_PCT_RANK":1,"PACE_RANK":1,"PIE_RANK":1},"PlayersSeasonTotals":{"0":{"GROUP_SET":"Players","PLAYER_ID":1559,"PLAYER_NAME":"Adrian Griffin","GP":4,"W":2,"L":2,"W_PCT":0.5,"MIN":14.2,"E_OFF_RATING":108.5,"OFF_RATING":107,"sp_work_OFF_RATING":107,"E_DEF_RATING":121.8,"DEF_RATING":122.4,"sp_work_DEF_RATING":122.4,"E_NET_RATING":-13.3,"NET_RATING":-15.4,"sp_work_NET_RATING":-15.4,"AST_PCT":0.105,"AST_TO":1.33,"AST_RATIO":16,"OREB_PCT":0.038,"DREB_PCT":0.13,"REB_PCT":0.084,"TM_TOV_PCT":12,"E_TOV_PCT":12.1,"EFG_PCT":0.588,"TS_PCT":0.559,"USG_PCT":0.165,"E_USG_PCT":0.171,"E_PACE":96.78,"PACE":97.19,"PACE_PER40":80.99,"sp_work_PACE":97.19,"PIE":0.072,"POSS":114,"FGM":10,"FGA":17,"FGM_PG":2.5,"FGA_PG":4.3,"FG_PCT":0.588,"GP_RANK":10,"W_RANK":10,"L_RANK":2,"W_PCT_RANK":2,"MIN_RANK":8,"E_OFF_RATING_RANK":5,"OFF_RATING_RANK":6,"sp_work_OFF_RATING_RANK":6,"E_DEF_RATING_RANK":9,"DEF_RATING_RANK":11,"sp_work_DEF_RATING_RANK":11,"E_NET_RATING_RANK":9,"NET_RATING_RANK":10,"sp_work_NET_RATING_RANK":10,"AST_PCT_RANK":6,"AST_TO_RANK":3,"AST_RATIO_RANK":5,"OREB_PCT_RANK":7,"DREB_PCT_RANK":4,"REB_PCT_RANK":7,"TM_TOV_PCT_RANK":10,"E_TOV_PCT_RANK":10,"EFG_PCT_RANK":2,"TS_PCT_RANK":5,"USG_PCT_RANK":6,"E_USG_PCT_RANK":6,"E_PACE_RANK":11,"PACE_RANK":11,"sp_work_PACE_RANK":11,"PIE_RANK":5,"FGM_RANK":8,"FGA_RANK":8,"FGM_PG_RANK":6,"FGA_PG_RANK":6,"FG_PCT_RANK":2},"1":{"GROUP_SET":"Players","PLAYER_ID":1717,"PLAYER_NAME":"Dirk Nowitzki","GP":8,"W":4,"L":4,"W_PCT":0.5,"MIN":44.6,"E_OFF_RATING":107.1,"OFF_RATING":108.9,"sp_work_OFF_RATING":108.9,"E_DEF_RATING":109.7,"DEF_RATING":110.8,"sp_work_DEF_RATING":110.8,"E_NET_RATING":-2.6,"NET_RATING":-1.8,"sp_work_NET_RATING":-1.8,"AST_PCT":0.082,"AST_TO":0.82,"AST_RATIO":7.6,"OREB_PCT":0.047,"DREB_PCT":0.238,"REB_PCT":0.143,"TM_TOV_PCT":9.3,"E_TOV_PCT":9.3,"EFG_PCT":0.494,"TS_PCT":0.577,"USG_PCT":0.266,"E_USG_PCT":0.269,"E_PACE":98.92,"PACE":97.59,"PACE_PER40":81.33,"sp_work_PACE":97.59,"PIE":0.167,"POSS":727,"FGM":73,"FGA":164,"FGM_PG":9.1,"FGA_PG":20.5,"FG_PCT":0.445,"GP_RANK":1,"W_RANK":1,"L_RANK":4,"W_PCT_RANK":2,"MIN_RANK":2,"E_OFF_RATING_RANK":7,"OFF_RATING_RANK":5,"sp_work_OFF_RATING_RANK":5,"E_DEF_RATING_RANK":7,"DEF_RATING_RANK":8,"sp_work_DEF_RATING_RANK":8,"E_NET_RATING_RANK":6,"NET_RATING_RANK":7,"sp_work_NET_RATING_RANK":7,"AST_PCT_RANK":7,"AST_TO_RANK":7,"AST_RATIO_RANK":9,"OREB_PCT_RANK":6,"DREB_PCT_RANK":1,"REB_PCT_RANK":1,"TM_TOV_PCT_RANK":9,"E_TOV_PCT_RANK":9,"EFG_PCT_RANK":8,"TS_PCT_RANK":4,"USG_PCT_RANK":1,"E_USG_PCT_RANK":1,"E_PACE_RANK":8,"PACE_RANK":9,"sp_work_PACE_RANK":9,"PIE_RANK":1,"FGM_RANK":1,"FGA_RANK":1,"FGM_PG_RANK":1,"FGA_PG_RANK":1,"FG_PCT_RANK":7},"2":{"GROUP_SET":"Players","PLAYER_ID":2059,"PLAYER_NAME":"Eduardo Najera","GP":8,"W":4,"L":4,"W_PCT":0.5,"MIN":15.4,"E_OFF_RATING":104.9,"OFF_RATING":105.5,"sp_work_OFF_RATING":105.5,"E_DEF_RATING":104.5,"DEF_RATING":102.3,"sp_work_DEF_RATING":102.3,"E_NET_RATING":0.4,"NET_RATING":3.2,"sp_work_NET_RATING":3.2,"AST_PCT":0.013,"AST_TO":0.5,"AST_RATIO":3.3,"OREB_PCT":0.023,"DREB_PCT":0.075,"REB_PCT":0.049,"TM_TOV_PCT":6.7,"E_TOV_PCT":6.8,"EFG_PCT":0.696,"TS_PCT":0.698,"USG_PCT":0.103,"E_USG_PCT":0.103,"E_PACE":99.58,"PACE":100.32,"PACE_PER40":83.6,"sp_work_PACE":100.32,"PIE":0.047,"POSS":254,"FGM":16,"FGA":23,"FGM_PG":2,"FGA_PG":2.9,"FG_PCT":0.696,"GP_RANK":1,"W_RANK":1,"L_RANK":4,"W_PCT_RANK":2,"MIN_RANK":6,"E_OFF_RATING_RANK":9,"OFF_RATING_RANK":8,"sp_work_OFF_RATING_RANK":8,"E_DEF_RATING_RANK":1,"DEF_RATING_RANK":1,"sp_work_DEF_RATING_RANK":1,"E_NET_RATING_RANK":4,"NET_RATING_RANK":4,"sp_work_NET_RATING_RANK":4,"AST_PCT_RANK":11,"AST_TO_RANK":8,"AST_RATIO_RANK":11,"OREB_PCT_RANK":10,"DREB_PCT_RANK":8,"REB_PCT_RANK":9,"TM_TOV_PCT_RANK":5,"E_TOV_PCT_RANK":5,"EFG_PCT_RANK":1,"TS_PCT_RANK":1,"USG_PCT_RANK":11,"E_USG_PCT_RANK":11,"E_PACE_RANK":4,"PACE_RANK":6,"sp_work_PACE_RANK":6,"PIE_RANK":9,"FGM_RANK":6,"FGA_RANK":7,"FGM_PG_RANK":7,"FGA_PG_RANK":8,"FG_PCT_RANK":1},"3":{"GROUP_SET":"Players","PLAYER_ID":1915,"PLAYER_NAME":"Evan Eschmeyer","GP":3,"W":2,"L":1,"W_PCT":0.667,"MIN":2.5,"E_OFF_RATING":83.1,"OFF_RATING":81.3,"sp_work_OFF_RATING":81.3,"E_DEF_RATING":126,"DEF_RATING":118.8,"sp_work_DEF_RATING":118.8,"E_NET_RATING":-42.9,"NET_RATING":-37.5,"sp_work_NET_RATING":-37.5,"AST_PCT":0.25,"AST_TO":0,"AST_RATIO":50,"OREB_PCT":0.143,"DREB_PCT":0.125,"REB_PCT":0.133,"TM_TOV_PCT":0,"E_TOV_PCT":0,"EFG_PCT":0,"TS_PCT":0,"USG_PCT":0.059,"E_USG_PCT":0.06,"E_PACE":99.43,"PACE":103.57,"PACE_PER40":86.31,"sp_work_PACE":103.57,"PIE":0,"POSS":16,"FGM":0,"FGA":1,"FGM_PG":0,"FGA_PG":0.3,"FG_PCT":0,"GP_RANK":11,"W_RANK":10,"L_RANK":1,"W_PCT_RANK":1,"MIN_RANK":12,"E_OFF_RATING_RANK":11,"OFF_RATING_RANK":11,"sp_work_OFF_RATING_RANK":11,"E_DEF_RATING_RANK":11,"DEF_RATING_RANK":10,"sp_work_DEF_RATING_RANK":10,"E_NET_RATING_RANK":11,"NET_RATING_RANK":11,"sp_work_NET_RATING_RANK":11,"AST_PCT_RANK":2,"AST_TO_RANK":9,"AST_RATIO_RANK":1,"OREB_PCT_RANK":1,"DREB_PCT_RANK":5,"REB_PCT_RANK":2,"TM_TOV_PCT_RANK":1,"E_TOV_PCT_RANK":1,"EFG_PCT_RANK":12,"TS_PCT_RANK":12,"USG_PCT_RANK":12,"E_USG_PCT_RANK":12,"E_PACE_RANK":5,"PACE_RANK":1,"sp_work_PACE_RANK":1,"PIE_RANK":10,"FGM_RANK":12,"FGA_RANK":12,"FGM_PG_RANK":12,"FGA_PG_RANK":12,"FG_PCT_RANK":12},"4":{"GROUP_SET":"Players","PLAYER_ID":1761,"PLAYER_NAME":"Greg Buckner","GP":7,"W":3,"L":4,"W_PCT":0.429,"MIN":15.1,"E_OFF_RATING":107.3,"OFF_RATING":106.8,"sp_work_OFF_RATING":106.8,"E_DEF_RATING":111.5,"DEF_RATING":107.8,"sp_work_DEF_RATING":107.8,"E_NET_RATING":-4.1,"NET_RATING":-1,"sp_work_NET_RATING":-1,"AST_PCT":0.056,"AST_TO":1.33,"AST_RATIO":11.8,"OREB_PCT":0.117,"DREB_PCT":0.121,"REB_PCT":0.119,"TM_TOV_PCT":8.8,"E_TOV_PCT":8.9,"EFG_PCT":0.48,"TS_PCT":0.504,"USG_PCT":0.117,"E_USG_PCT":0.119,"E_PACE":100.25,"PACE":102.19,"PACE_PER40":85.16,"sp_work_PACE":102.19,"PIE":0.064,"POSS":220,"FGM":12,"FGA":25,"FGM_PG":1.7,"FGA_PG":3.6,"FG_PCT":0.48,"GP_RANK":8,"W_RANK":8,"L_RANK":4,"W_PCT_RANK":10,"MIN_RANK":7,"E_OFF_RATING_RANK":6,"OFF_RATING_RANK":7,"sp_work_OFF_RATING_RANK":7,"E_DEF_RATING_RANK":8,"DEF_RATING_RANK":5,"sp_work_DEF_RATING_RANK":5,"E_NET_RATING_RANK":7,"NET_RATING_RANK":6,"sp_work_NET_RATING_RANK":6,"AST_PCT_RANK":9,"AST_TO_RANK":3,"AST_RATIO_RANK":7,"OREB_PCT_RANK":2,"DREB_PCT_RANK":6,"REB_PCT_RANK":5,"TM_TOV_PCT_RANK":8,"E_TOV_PCT_RANK":8,"EFG_PCT_RANK":9,"TS_PCT_RANK":8,"USG_PCT_RANK":10,"E_USG_PCT_RANK":10,"E_PACE_RANK":2,"PACE_RANK":4,"sp_work_PACE_RANK":4,"PIE_RANK":6,"FGM_RANK":7,"FGA_RANK":6,"FGM_PG_RANK":8,"FGA_PG_RANK":7,"FG_PCT_RANK":5},"5":{"GROUP_SET":"Players","PLAYER_ID":271,"PLAYER_NAME":"Johnny Newman","GP":3,"W":1,"L":2,"W_PCT":0.333,"MIN":7.5,"E_OFF_RATING":81.4,"OFF_RATING":76.6,"sp_work_OFF_RATING":76.6,"E_DEF_RATING":137.5,"DEF_RATING":127.1,"sp_work_DEF_RATING":127.1,"E_NET_RATING":-56.1,"NET_RATING":-50.5,"sp_work_NET_RATING":-50.5,"AST_PCT":0.133,"AST_TO":0,"AST_RATIO":22.2,"OREB_PCT":0,"DREB_PCT":0,"REB_PCT":0,"TM_TOV_PCT":0,"E_TOV_PCT":0,"EFG_PCT":0.214,"TS_PCT":0.214,"USG_PCT":0.137,"E_USG_PCT":0.145,"E_PACE":94.61,"PACE":101.49,"PACE_PER40":84.58,"sp_work_PACE":101.49,"PIE":-0.079,"POSS":47,"FGM":1,"FGA":7,"FGM_PG":0.3,"FGA_PG":2.3,"FG_PCT":0.143,"GP_RANK":11,"W_RANK":12,"L_RANK":2,"W_PCT_RANK":12,"MIN_RANK":9,"E_OFF_RATING_RANK":12,"OFF_RATING_RANK":12,"sp_work_OFF_RATING_RANK":12,"E_DEF_RATING_RANK":12,"DEF_RATING_RANK":12,"sp_work_DEF_RATING_RANK":12,"E_NET_RATING_RANK":12,"NET_RATING_RANK":12,"sp_work_NET_RATING_RANK":12,"AST_PCT_RANK":4,"AST_TO_RANK":9,"AST_RATIO_RANK":3,"OREB_PCT_RANK":12,"DREB_PCT_RANK":12,"REB_PCT_RANK":12,"TM_TOV_PCT_RANK":1,"E_TOV_PCT_RANK":1,"EFG_PCT_RANK":11,"TS_PCT_RANK":11,"USG_PCT_RANK":8,"E_USG_PCT_RANK":8,"E_PACE_RANK":12,"PACE_RANK":5,"sp_work_PACE_RANK":5,"PIE_RANK":12,"FGM_RANK":11,"FGA_RANK":10,"FGM_PG_RANK":11,"FGA_PG_RANK":9,"FG_PCT_RANK":11},"6":{"GROUP_SET":"Players","PLAYER_ID":714,"PLAYER_NAME":"Michael Finley","GP":8,"W":4,"L":4,"W_PCT":0.5,"MIN":46.5,"E_OFF_RATING":108.8,"OFF_RATING":110.4,"sp_work_OFF_RATING":110.4,"E_DEF_RATING":109.5,"DEF_RATING":110.4,"sp_work_DEF_RATING":110.4,"E_NET_RATING":-0.8,"NET_RATING":0.1,"sp_work_NET_RATING":0.1,"AST_PCT":0.077,"AST_TO":1.2,"AST_RATIO":8.9,"OREB_PCT":0.034,"DREB_PCT":0.096,"REB_PCT":0.065,"TM_TOV_PCT":7.4,"E_TOV_PCT":7.4,"EFG_PCT":0.514,"TS_PCT":0.579,"USG_PCT":0.215,"E_USG_PCT":0.217,"E_PACE":98.49,"PACE":97.35,"PACE_PER40":81.13,"sp_work_PACE":97.35,"PIE":0.115,"POSS":756,"FGM":69,"FGA":148,"FGM_PG":8.6,"FGA_PG":18.5,"FG_PCT":0.466,"GP_RANK":1,"W_RANK":1,"L_RANK":4,"W_PCT_RANK":2,"MIN_RANK":1,"E_OFF_RATING_RANK":4,"OFF_RATING_RANK":4,"sp_work_OFF_RATING_RANK":4,"E_DEF_RATING_RANK":6,"DEF_RATING_RANK":7,"sp_work_DEF_RATING_RANK":7,"E_NET_RATING_RANK":5,"NET_RATING_RANK":5,"sp_work_NET_RATING_RANK":5,"AST_PCT_RANK":8,"AST_TO_RANK":5,"AST_RATIO_RANK":8,"OREB_PCT_RANK":8,"DREB_PCT_RANK":7,"REB_PCT_RANK":8,"TM_TOV_PCT_RANK":6,"E_TOV_PCT_RANK":6,"EFG_PCT_RANK":6,"TS_PCT_RANK":3,"USG_PCT_RANK":2,"E_USG_PCT_RANK":2,"E_PACE_RANK":9,"PACE_RANK":10,"sp_work_PACE_RANK":10,"PIE_RANK":3,"FGM_RANK":2,"FGA_RANK":2,"FGM_PG_RANK":2,"FGA_PG_RANK":2,"FG_PCT_RANK":6},"7":{"GROUP_SET":"Players","PLAYER_ID":89,"PLAYER_NAME":"Nick Van Exel","GP":8,"W":4,"L":4,"W_PCT":0.5,"MIN":32.8,"E_OFF_RATING":111.3,"OFF_RATING":113.1,"sp_work_OFF_RATING":113.1,"E_DEF_RATING":107.9,"DEF_RATING":107.2,"sp_work_DEF_RATING":107.2,"E_NET_RATING":3.4,"NET_RATING":5.9,"sp_work_NET_RATING":5.9,"AST_PCT":0.171,"AST_TO":2.58,"AST_RATIO":20.8,"OREB_PCT":0.025,"DREB_PCT":0.061,"REB_PCT":0.043,"TM_TOV_PCT":8.1,"E_TOV_PCT":8,"EFG_PCT":0.401,"TS_PCT":0.419,"USG_PCT":0.19,"E_USG_PCT":0.193,"E_PACE":99.28,"PACE":98.76,"PACE_PER40":82.3,"sp_work_PACE":98.76,"PIE":0.047,"POSS":542,"FGM":37,"FGA":101,"FGM_PG":4.6,"FGA_PG":12.6,"FG_PCT":0.366,"GP_RANK":1,"W_RANK":1,"L_RANK":4,"W_PCT_RANK":2,"MIN_RANK":4,"E_OFF_RATING_RANK":1,"OFF_RATING_RANK":2,"sp_work_OFF_RATING_RANK":2,"E_DEF_RATING_RANK":4,"DEF_RATING_RANK":4,"sp_work_DEF_RATING_RANK":4,"E_NET_RATING_RANK":1,"NET_RATING_RANK":2,"sp_work_NET_RATING_RANK":2,"AST_PCT_RANK":3,"AST_TO_RANK":1,"AST_RATIO_RANK":4,"OREB_PCT_RANK":9,"DREB_PCT_RANK":11,"REB_PCT_RANK":11,"TM_TOV_PCT_RANK":7,"E_TOV_PCT_RANK":7,"EFG_PCT_RANK":10,"TS_PCT_RANK":10,"USG_PCT_RANK":4,"E_USG_PCT_RANK":4,"E_PACE_RANK":7,"PACE_RANK":8,"sp_work_PACE_RANK":8,"PIE_RANK":8,"FGM_RANK":5,"FGA_RANK":4,"FGM_PG_RANK":5,"FGA_PG_RANK":4,"FG_PCT_RANK":10},"8":{"GROUP_SET":"Players","PLAYER_ID":1711,"PLAYER_NAME":"Raef LaFrentz","GP":8,"W":4,"L":4,"W_PCT":0.5,"MIN":30.7,"E_OFF_RATING":111.2,"OFF_RATING":113.1,"sp_work_OFF_RATING":113.1,"E_DEF_RATING":108.3,"DEF_RATING":108.1,"sp_work_DEF_RATING":108.1,"E_NET_RATING":3,"NET_RATING":5.1,"sp_work_NET_RATING":5.1,"AST_PCT":0.029,"AST_TO":0.83,"AST_RATIO":5.4,"OREB_PCT":0.07,"DREB_PCT":0.17,"REB_PCT":0.12,"TM_TOV_PCT":6.5,"E_TOV_PCT":6.4,"EFG_PCT":0.538,"TS_PCT":0.543,"USG_PCT":0.154,"E_USG_PCT":0.157,"E_PACE":97.42,"PACE":96.69,"PACE_PER40":80.57,"sp_work_PACE":96.69,"PIE":0.078,"POSS":495,"FGM":39,"FGA":78,"FGM_PG":4.9,"FGA_PG":9.8,"FG_PCT":0.5,"GP_RANK":1,"W_RANK":1,"L_RANK":4,"W_PCT_RANK":2,"MIN_RANK":5,"E_OFF_RATING_RANK":2,"OFF_RATING_RANK":1,"sp_work_OFF_RATING_RANK":1,"E_DEF_RATING_RANK":5,"DEF_RATING_RANK":6,"sp_work_DEF_RATING_RANK":6,"E_NET_RATING_RANK":2,"NET_RATING_RANK":3,"sp_work_NET_RATING_RANK":3,"AST_PCT_RANK":10,"AST_TO_RANK":6,"AST_RATIO_RANK":10,"OREB_PCT_RANK":4,"DREB_PCT_RANK":3,"REB_PCT_RANK":4,"TM_TOV_PCT_RANK":4,"E_TOV_PCT_RANK":4,"EFG_PCT_RANK":3,"TS_PCT_RANK":6,"USG_PCT_RANK":7,"E_USG_PCT_RANK":7,"E_PACE_RANK":10,"PACE_RANK":12,"sp_work_PACE_RANK":12,"PIE_RANK":4,"FGM_RANK":4,"FGA_RANK":5,"FGM_PG_RANK":4,"FGA_PG_RANK":5,"FG_PCT_RANK":3},"9":{"GROUP_SET":"Players","PLAYER_ID":762,"PLAYER_NAME":"Shawn Bradley","GP":7,"W":3,"L":4,"W_PCT":0.429,"MIN":3.6,"E_OFF_RATING":105.2,"OFF_RATING":103.9,"sp_work_OFF_RATING":103.9,"E_DEF_RATING":122.9,"DEF_RATING":117.2,"sp_work_DEF_RATING":117.2,"E_NET_RATING":-17.8,"NET_RATING":-13.3,"sp_work_NET_RATING":-13.3,"AST_PCT":0,"AST_TO":0,"AST_RATIO":0,"OREB_PCT":0.05,"DREB_PCT":0.19,"REB_PCT":0.122,"TM_TOV_PCT":14.3,"E_TOV_PCT":14.3,"EFG_PCT":0.5,"TS_PCT":0.5,"USG_PCT":0.132,"E_USG_PCT":0.134,"E_PACE":99.72,"PACE":102.81,"PACE_PER40":85.67,"sp_work_PACE":102.81,"PIE":-0.023,"POSS":51,"FGM":3,"FGA":6,"FGM_PG":0.4,"FGA_PG":0.9,"FG_PCT":0.5,"GP_RANK":8,"W_RANK":8,"L_RANK":4,"W_PCT_RANK":10,"MIN_RANK":11,"E_OFF_RATING_RANK":8,"OFF_RATING_RANK":9,"sp_work_OFF_RATING_RANK":9,"E_DEF_RATING_RANK":10,"DEF_RATING_RANK":9,"sp_work_DEF_RATING_RANK":9,"E_NET_RATING_RANK":10,"NET_RATING_RANK":9,"sp_work_NET_RATING_RANK":9,"AST_PCT_RANK":12,"AST_TO_RANK":9,"AST_RATIO_RANK":12,"OREB_PCT_RANK":5,"DREB_PCT_RANK":2,"REB_PCT_RANK":3,"TM_TOV_PCT_RANK":12,"E_TOV_PCT_RANK":12,"EFG_PCT_RANK":7,"TS_PCT_RANK":9,"USG_PCT_RANK":9,"E_USG_PCT_RANK":9,"E_PACE_RANK":3,"PACE_RANK":3,"sp_work_PACE_RANK":3,"PIE_RANK":11,"FGM_RANK":10,"FGA_RANK":11,"FGM_PG_RANK":10,"FGA_PG_RANK":11,"FG_PCT_RANK":3},"10":{"GROUP_SET":"Players","PLAYER_ID":959,"PLAYER_NAME":"Steve Nash","GP":8,"W":4,"L":4,"W_PCT":0.5,"MIN":40.5,"E_OFF_RATING":109.2,"OFF_RATING":111,"sp_work_OFF_RATING":111,"E_DEF_RATING":106.3,"DEF_RATING":105.1,"sp_work_DEF_RATING":105.1,"E_NET_RATING":2.9,"NET_RATING":5.9,"sp_work_NET_RATING":5.9,"AST_PCT":0.323,"AST_TO":2.33,"AST_RATIO":30.6,"OREB_PCT":0.021,"DREB_PCT":0.072,"REB_PCT":0.047,"TM_TOV_PCT":13.1,"E_TOV_PCT":12.9,"EFG_PCT":0.517,"TS_PCT":0.585,"USG_PCT":0.21,"E_USG_PCT":0.217,"E_PACE":99.38,"PACE":99.09,"PACE_PER40":82.58,"sp_work_PACE":99.09,"PIE":0.122,"POSS":670,"FGM":51,"FGA":118,"FGM_PG":6.4,"FGA_PG":14.8,"FG_PCT":0.432,"GP_RANK":1,"W_RANK":1,"L_RANK":4,"W_PCT_RANK":2,"MIN_RANK":3,"E_OFF_RATING_RANK":3,"OFF_RATING_RANK":3,"sp_work_OFF_RATING_RANK":3,"E_DEF_RATING_RANK":2,"DEF_RATING_RANK":3,"sp_work_DEF_RATING_RANK":3,"E_NET_RATING_RANK":3,"NET_RATING_RANK":1,"sp_work_NET_RATING_RANK":1,"AST_PCT_RANK":1,"AST_TO_RANK":2,"AST_RATIO_RANK":2,"OREB_PCT_RANK":11,"DREB_PCT_RANK":9,"REB_PCT_RANK":10,"TM_TOV_PCT_RANK":11,"E_TOV_PCT_RANK":11,"EFG_PCT_RANK":5,"TS_PCT_RANK":2,"USG_PCT_RANK":3,"E_USG_PCT_RANK":3,"E_PACE_RANK":6,"PACE_RANK":7,"sp_work_PACE_RANK":7,"PIE_RANK":2,"FGM_RANK":3,"FGA_RANK":3,"FGM_PG_RANK":3,"FGA_PG_RANK":3,"FG_PCT_RANK":9},"11":{"GROUP_SET":"Players","PLAYER_ID":1917,"PLAYER_NAME":"Wang Zhi-zhi","GP":8,"W":4,"L":4,"W_PCT":0.5,"MIN":5.4,"E_OFF_RATING":99.6,"OFF_RATING":97.8,"sp_work_OFF_RATING":97.8,"E_DEF_RATING":107.8,"DEF_RATING":104.2,"sp_work_DEF_RATING":104.2,"E_NET_RATING":-8.2,"NET_RATING":-6.4,"sp_work_NET_RATING":-6.4,"AST_PCT":0.125,"AST_TO":0,"AST_RATIO":13.6,"OREB_PCT":0.104,"DREB_PCT":0.064,"REB_PCT":0.084,"TM_TOV_PCT":0,"E_TOV_PCT":0,"EFG_PCT":0.531,"TS_PCT":0.536,"USG_PCT":0.186,"E_USG_PCT":0.188,"E_PACE":100.78,"PACE":103.47,"PACE_PER40":86.23,"sp_work_PACE":103.47,"PIE":0.049,"POSS":91,"FGM":7,"FGA":16,"FGM_PG":0.9,"FGA_PG":2,"FG_PCT":0.438,"GP_RANK":1,"W_RANK":1,"L_RANK":4,"W_PCT_RANK":2,"MIN_RANK":10,"E_OFF_RATING_RANK":10,"OFF_RATING_RANK":10,"sp_work_OFF_RATING_RANK":10,"E_DEF_RATING_RANK":3,"DEF_RATING_RANK":2,"sp_work_DEF_RATING_RANK":2,"E_NET_RATING_RANK":8,"NET_RATING_RANK":8,"sp_work_NET_RATING_RANK":8,"AST_PCT_RANK":5,"AST_TO_RANK":9,"AST_RATIO_RANK":6,"OREB_PCT_RANK":3,"DREB_PCT_RANK":10,"REB_PCT_RANK":6,"TM_TOV_PCT_RANK":1,"E_TOV_PCT_RANK":1,"EFG_PCT_RANK":4,"TS_PCT_RANK":7,"USG_PCT_RANK":5,"E_USG_PCT_RANK":5,"E_PACE_RANK":1,"PACE_RANK":2,"sp_work_PACE_RANK":2,"PIE_RANK":7,"FGM_RANK":9,"FGA_RANK":9,"FGM_PG_RANK":9,"FGA_PG_RANK":10,"FG_PCT_RANK":8}}}