{"TeamOverall":{"GROUP_SET":"Overall","TEAM_ID":1610612754,"TEAM_NAME":"Indiana Pacers","GROUP_VALUE":"2011-12","GP":66,"W":42,"L":24,"W_PCT":0.636,"MIN":3198,"E_OFF_RATING":103.5,"OFF_RATING":105.5,"E_DEF_RATING":100.4,"DEF_RATING":102.1,"E_NET_RATING":3.1,"NET_RATING":3.3,"AST_PCT":0.522,"AST_TO":1.33,"AST_RATIO":14.7,"OREB_PCT":0.333,"DREB_PCT":0.689,"REB_PCT":0.511,"TM_TOV_PCT":0.151,"EFG_PCT":0.474,"TS_PCT":0.526,"E_PACE":93.4,"PACE":91.68,"PACE_PER40":76.4,"POSS":6115,"PIE":0.521,"GP_RANK":1,"W_RANK":1,"L_RANK":1,"W_PCT_RANK":1,"MIN_RANK":1,"OFF_RATING_RANK":1,"DEF_RATING_RANK":1,"NET_RATING_RANK":1,"AST_PCT_RANK":1,"AST_TO_RANK":1,"AST_RATIO_RANK":1,"OREB_PCT_RANK":1,"DREB_PCT_RANK":1,"REB_PCT_RANK":1,"TM_TOV_PCT_RANK":1,"EFG_PCT_RANK":1,"TS_PCT_RANK":1,"PACE_RANK":1,"PIE_RANK":1},"PlayersSeasonTotals":{"0":{"GROUP_SET":"Players","PLAYER_ID":201985,"PLAYER_NAME":"AJ Price","GP":44,"W":27,"L":17,"W_PCT":0.614,"MIN":12.9,"E_OFF_RATING":99.1,"OFF_RATING":98.9,"sp_work_OFF_RATING":98.9,"E_DEF_RATING":98.7,"DEF_RATING":97.7,"sp_work_DEF_RATING":97.7,"E_NET_RATING":0.4,"NET_RATING":1.2,"sp_work_NET_RATING":1.2,"AST_PCT":0.264,"AST_TO":2.69,"AST_RATIO":28,"OREB_PCT":0.021,"DREB_PCT":0.092,"REB_PCT":0.054,"TM_TOV_PCT":10.4,"E_TOV_PCT":10.4,"EFG_PCT":0.414,"TS_PCT":0.454,"USG_PCT":0.171,"E_USG_PCT":0.175,"E_PACE":92.93,"PACE":93.5,"PACE_PER40":77.92,"sp_work_PACE":93.5,"PIE":0.095,"POSS":1118,"FGM":59,"FGA":174,"FGM_PG":1.3,"FGA_PG":4,"FG_PCT":0.339,"GP_RANK":10,"W_RANK":10,"L_RANK":6,"W_PCT_RANK":13,"MIN_RANK":10,"E_OFF_RATING_RANK":11,"OFF_RATING_RANK":11,"sp_work_OFF_RATING_RANK":11,"E_DEF_RATING_RANK":3,"DEF_RATING_RANK":3,"sp_work_DEF_RATING_RANK":3,"E_NET_RATING_RANK":9,"NET_RATING_RANK":10,"sp_work_NET_RATING_RANK":10,"AST_PCT_RANK":1,"AST_TO_RANK":2,"AST_RATIO_RANK":2,"OREB_PCT_RANK":14,"DREB_PCT_RANK":12,"REB_PCT_RANK":14,"TM_TOV_PCT_RANK":8,"E_TOV_PCT_RANK":8,"EFG_PCT_RANK":12,"TS_PCT_RANK":12,"USG_PCT_RANK":8,"E_USG_PCT_RANK":8,"E_PACE_RANK":8,"PACE_RANK":7,"sp_work_PACE_RANK":7,"PIE_RANK":8,"FGM_RANK":11,"FGA_RANK":11,"FGM_PG_RANK":11,"FGA_PG_RANK":10,"FG_PCT_RANK":15},"1":{"GROUP_SET":"Players","PLAYER_ID":2563,"PLAYER_NAME":"Dahntay Jones","GP":65,"W":42,"L":23,"W_PCT":0.646,"MIN":16.2,"E_OFF_RATING":98.8,"OFF_RATING":98.9,"sp_work_OFF_RATING":98.9,"E_DEF_RATING":102.9,"DEF_RATING":103,"sp_work_DEF_RATING":103,"E_NET_RATING":-4,"NET_RATING":-4.2,"sp_work_NET_RATING":-4.2,"AST_PCT":0.106,"AST_TO":1.37,"AST_RATIO":14.7,"OREB_PCT":0.021,"DREB_PCT":0.093,"REB_PCT":0.056,"TM_TOV_PCT":10.7,"E_TOV_PCT":10.6,"EFG_PCT":0.468,"TS_PCT":0.533,"USG_PCT":0.156,"E_USG_PCT":0.162,"E_PACE":92.51,"PACE":92.42,"PACE_PER40":77.02,"sp_work_PACE":92.42,"PIE":0.066,"POSS":2031,"FGM":115,"FGA":281,"FGM_PG":1.8,"FGA_PG":4.3,"FG_PCT":0.409,"GP_RANK":4,"W_RANK":1,"L_RANK":10,"W_PCT_RANK":7,"MIN_RANK":9,"E_OFF_RATING_RANK":12,"OFF_RATING_RANK":12,"sp_work_OFF_RATING_RANK":12,"E_DEF_RATING_RANK":13,"DEF_RATING_RANK":13,"sp_work_DEF_RATING_RANK":13,"E_NET_RATING_RANK":14,"NET_RATING_RANK":15,"sp_work_NET_RATING_RANK":15,"AST_PCT_RANK":8,"AST_TO_RANK":6,"AST_RATIO_RANK":6,"OREB_PCT_RANK":13,"DREB_PCT_RANK":11,"REB_PCT_RANK":12,"TM_TOV_PCT_RANK":9,"E_TOV_PCT_RANK":9,"EFG_PCT_RANK":8,"TS_PCT_RANK":6,"USG_PCT_RANK":14,"E_USG_PCT_RANK":14,"E_PACE_RANK":11,"PACE_RANK":12,"sp_work_PACE_RANK":12,"PIE_RANK":13,"FGM_RANK":8,"FGA_RANK":8,"FGM_PG_RANK":9,"FGA_PG_RANK":9,"FG_PCT_RANK":10},"2":{"GROUP_SET":"Players","PLAYER_ID":101122,"PLAYER_NAME":"Danny Granger","GP":62,"W":41,"L":21,"W_PCT":0.661,"MIN":33.3,"E_OFF_RATING":106.4,"OFF_RATING":107.7,"sp_work_OFF_RATING":107.7,"E_DEF_RATING":99.2,"DEF_RATING":100.6,"sp_work_DEF_RATING":100.6,"E_NET_RATING":7.2,"NET_RATING":7,"sp_work_NET_RATING":7,"AST_PCT":0.091,"AST_TO":0.99,"AST_RATIO":8.5,"OREB_PCT":0.039,"DREB_PCT":0.108,"REB_PCT":0.074,"TM_TOV_PCT":8.6,"E_TOV_PCT":8.5,"EFG_PCT":0.481,"TS_PCT":0.542,"USG_PCT":0.252,"E_USG_PCT":0.257,"E_PACE":94.02,"PACE":92.78,"PACE_PER40":77.32,"sp_work_PACE":92.78,"PIE":0.117,"POSS":3993,"FGM":391,"FGA":941,"FGM_PG":6.3,"FGA_PG":15.2,"FG_PCT":0.416,"GP_RANK":6,"W_RANK":5,"L_RANK":8,"W_PCT_RANK":5,"MIN_RANK":1,"E_OFF_RATING_RANK":3,"OFF_RATING_RANK":2,"sp_work_OFF_RATING_RANK":2,"E_DEF_RATING_RANK":4,"DEF_RATING_RANK":6,"sp_work_DEF_RATING_RANK":6,"E_NET_RATING_RANK":2,"NET_RATING_RANK":3,"sp_work_NET_RATING_RANK":3,"AST_PCT_RANK":11,"AST_TO_RANK":10,"AST_RATIO_RANK":13,"OREB_PCT_RANK":8,"DREB_PCT_RANK":9,"REB_PCT_RANK":9,"TM_TOV_PCT_RANK":4,"E_TOV_PCT_RANK":4,"EFG_PCT_RANK":6,"TS_PCT_RANK":4,"USG_PCT_RANK":1,"E_USG_PCT_RANK":1,"E_PACE_RANK":3,"PACE_RANK":9,"sp_work_PACE_RANK":9,"PIE_RANK":5,"FGM_RANK":1,"FGA_RANK":1,"FGM_PG_RANK":1,"FGA_PG_RANK":1,"FG_PCT_RANK":9},"3":{"GROUP_SET":"Players","PLAYER_ID":201954,"PLAYER_NAME":"Darren Collison","GP":60,"W":36,"L":24,"W_PCT":0.6,"MIN":31.3,"E_OFF_RATING":104.1,"OFF_RATING":105.4,"sp_work_OFF_RATING":105.4,"E_DEF_RATING":100.6,"DEF_RATING":102,"sp_work_DEF_RATING":102,"E_NET_RATING":3.5,"NET_RATING":3.4,"sp_work_NET_RATING":3.4,"AST_PCT":0.239,"AST_TO":2.52,"AST_RATIO":29,"OREB_PCT":0.016,"DREB_PCT":0.082,"REB_PCT":0.05,"TM_TOV_PCT":11.5,"E_TOV_PCT":11.5,"EFG_PCT":0.472,"TS_PCT":0.526,"USG_PCT":0.167,"E_USG_PCT":0.17,"E_PACE":94.04,"PACE":92.78,"PACE_PER40":77.32,"sp_work_PACE":92.78,"PIE":0.1,"POSS":3629,"FGM":230,"FGA":523,"FGM_PG":3.8,"FGA_PG":8.7,"FG_PCT":0.44,"GP_RANK":7,"W_RANK":8,"L_RANK":11,"W_PCT_RANK":14,"MIN_RANK":2,"E_OFF_RATING_RANK":9,"OFF_RATING_RANK":8,"sp_work_OFF_RATING_RANK":8,"E_DEF_RATING_RANK":8,"DEF_RATING_RANK":11,"sp_work_DEF_RATING_RANK":11,"E_NET_RATING_RANK":7,"NET_RATING_RANK":8,"sp_work_NET_RATING_RANK":8,"AST_PCT_RANK":2,"AST_TO_RANK":3,"AST_RATIO_RANK":1,"OREB_PCT_RANK":15,"DREB_PCT_RANK":15,"REB_PCT_RANK":15,"TM_TOV_PCT_RANK":10,"E_TOV_PCT_RANK":10,"EFG_PCT_RANK":7,"TS_PCT_RANK":8,"USG_PCT_RANK":10,"E_USG_PCT_RANK":12,"E_PACE_RANK":2,"PACE_RANK":10,"sp_work_PACE_RANK":10,"PIE_RANK":7,"FGM_RANK":5,"FGA_RANK":5,"FGM_PG_RANK":5,"FGA_PG_RANK":5,"FG_PCT_RANK":5},"4":{"GROUP_SET":"Players","PLAYER_ID":2561,"PLAYER_NAME":"David West","GP":66,"W":42,"L":24,"W_PCT":0.636,"MIN":29.2,"E_OFF_RATING":105,"OFF_RATING":106,"sp_work_OFF_RATING":106,"E_DEF_RATING":99.6,"DEF_RATING":100.4,"sp_work_DEF_RATING":100.4,"E_NET_RATING":5.4,"NET_RATING":5.6,"sp_work_NET_RATING":5.6,"AST_PCT":0.123,"AST_TO":1.51,"AST_RATIO":13.6,"OREB_PCT":0.062,"DREB_PCT":0.16,"REB_PCT":0.112,"TM_TOV_PCT":9,"E_TOV_PCT":9.1,"EFG_PCT":0.489,"TS_PCT":0.531,"USG_PCT":0.207,"E_USG_PCT":0.209,"E_PACE":93.57,"PACE":92.69,"PACE_PER40":77.24,"sp_work_PACE":92.69,"PIE":0.125,"POSS":3721,"FGM":349,"FGA":716,"FGM_PG":5.3,"FGA_PG":10.8,"FG_PCT":0.487,"GP_RANK":1,"W_RANK":1,"L_RANK":11,"W_PCT_RANK":8,"MIN_RANK":5,"E_OFF_RATING_RANK":6,"OFF_RATING_RANK":4,"sp_work_OFF_RATING_RANK":4,"E_DEF_RATING_RANK":6,"DEF_RATING_RANK":5,"sp_work_DEF_RATING_RANK":5,"E_NET_RATING_RANK":6,"NET_RATING_RANK":5,"sp_work_NET_RATING_RANK":5,"AST_PCT_RANK":7,"AST_TO_RANK":5,"AST_RATIO_RANK":7,"OREB_PCT_RANK":7,"DREB_PCT_RANK":6,"REB_PCT_RANK":6,"TM_TOV_PCT_RANK":5,"E_TOV_PCT_RANK":5,"EFG_PCT_RANK":5,"TS_PCT_RANK":7,"USG_PCT_RANK":5,"E_USG_PCT_RANK":5,"E_PACE_RANK":5,"PACE_RANK":11,"sp_work_PACE_RANK":11,"PIE_RANK":2,"FGM_RANK":2,"FGA_RANK":2,"FGM_PG_RANK":2,"FGA_PG_RANK":2,"FG_PCT_RANK":3},"5":{"GROUP_SET":"Players","PLAYER_ID":201588,"PLAYER_NAME":"George Hill","GP":50,"W":35,"L":15,"W_PCT":0.7,"MIN":25.5,"E_OFF_RATING":104.5,"OFF_RATING":105.7,"sp_work_OFF_RATING":105.7,"E_DEF_RATING":101.5,"DEF_RATING":101.5,"sp_work_DEF_RATING":101.5,"E_NET_RATING":3.1,"NET_RATING":4.2,"sp_work_NET_RATING":4.2,"AST_PCT":0.194,"AST_TO":2.79,"AST_RATIO":23.1,"OREB_PCT":0.024,"DREB_PCT":0.091,"REB_PCT":0.058,"TM_TOV_PCT":8.3,"E_TOV_PCT":8.3,"EFG_PCT":0.513,"TS_PCT":0.557,"USG_PCT":0.169,"E_USG_PCT":0.173,"E_PACE":92,"PACE":91.49,"PACE_PER40":76.24,"sp_work_PACE":91.49,"PIE":0.112,"POSS":2417,"FGM":168,"FGA":380,"FGM_PG":3.4,"FGA_PG":7.6,"FG_PCT":0.442,"GP_RANK":9,"W_RANK":9,"L_RANK":5,"W_PCT_RANK":4,"MIN_RANK":6,"E_OFF_RATING_RANK":7,"OFF_RATING_RANK":6,"sp_work_OFF_RATING_RANK":6,"E_DEF_RATING_RANK":9,"DEF_RATING_RANK":10,"sp_work_DEF_RATING_RANK":10,"E_NET_RATING_RANK":8,"NET_RATING_RANK":7,"sp_work_NET_RATING_RANK":7,"AST_PCT_RANK":3,"AST_TO_RANK":1,"AST_RATIO_RANK":3,"OREB_PCT_RANK":12,"DREB_PCT_RANK":13,"REB_PCT_RANK":11,"TM_TOV_PCT_RANK":3,"E_TOV_PCT_RANK":3,"EFG_PCT_RANK":2,"TS_PCT_RANK":2,"USG_PCT_RANK":9,"E_USG_PCT_RANK":9,"E_PACE_RANK":13,"PACE_RANK":15,"sp_work_PACE_RANK":15,"PIE_RANK":6,"FGM_RANK":7,"FGA_RANK":7,"FGM_PG_RANK":6,"FGA_PG_RANK":7,"FG_PCT_RANK":4},"6":{"GROUP_SET":"Players","PLAYER_ID":201965,"PLAYER_NAME":"Jeff Ayres","GP":20,"W":13,"L":7,"W_PCT":0.65,"MIN":5.3,"E_OFF_RATING":107,"OFF_RATING":105.7,"sp_work_OFF_RATING":105.7,"E_DEF_RATING":107.8,"DEF_RATING":103.4,"sp_work_DEF_RATING":103.4,"E_NET_RATING":-0.8,"NET_RATING":2.3,"sp_work_NET_RATING":2.3,"AST_PCT":0.063,"AST_TO":2,"AST_RATIO":8.9,"OREB_PCT":0.101,"DREB_PCT":0.2,"REB_PCT":0.147,"TM_TOV_PCT":4.4,"E_TOV_PCT":4.4,"EFG_PCT":0.417,"TS_PCT":0.435,"USG_PCT":0.162,"E_USG_PCT":0.169,"E_PACE":91.89,"PACE":94.37,"PACE_PER40":78.65,"sp_work_PACE":94.37,"PIE":0.076,"POSS":210,"FGM":15,"FGA":36,"FGM_PG":0.8,"FGA_PG":1.8,"FG_PCT":0.417,"GP_RANK":13,"W_RANK":13,"L_RANK":4,"W_PCT_RANK":6,"MIN_RANK":15,"E_OFF_RATING_RANK":2,"OFF_RATING_RANK":5,"sp_work_OFF_RATING_RANK":5,"E_DEF_RATING_RANK":15,"DEF_RATING_RANK":14,"sp_work_DEF_RATING_RANK":14,"E_NET_RATING_RANK":11,"NET_RATING_RANK":9,"sp_work_NET_RATING_RANK":9,"AST_PCT_RANK":12,"AST_TO_RANK":4,"AST_RATIO_RANK":12,"OREB_PCT_RANK":5,"DREB_PCT_RANK":2,"REB_PCT_RANK":4,"TM_TOV_PCT_RANK":2,"E_TOV_PCT_RANK":2,"EFG_PCT_RANK":11,"TS_PCT_RANK":14,"USG_PCT_RANK":13,"E_USG_PCT_RANK":13,"E_PACE_RANK":14,"PACE_RANK":2,"sp_work_PACE_RANK":2,"PIE_RANK":12,"FGM_RANK":13,"FGA_RANK":13,"FGM_PG_RANK":14,"FGA_PG_RANK":13,"FG_PCT_RANK":8},"7":{"GROUP_SET":"Players","PLAYER_ID":1902,"PLAYER_NAME":"Jeff Foster","GP":11,"W":8,"L":3,"W_PCT":0.727,"MIN":12.8,"E_OFF_RATING":97.1,"OFF_RATING":97.1,"sp_work_OFF_RATING":97.1,"E_DEF_RATING":90.3,"DEF_RATING":88.8,"sp_work_DEF_RATING":88.8,"E_NET_RATING":6.8,"NET_RATING":8.3,"sp_work_NET_RATING":8.3,"AST_PCT":0.051,"AST_TO":0.57,"AST_RATIO":12.1,"OREB_PCT":0.126,"DREB_PCT":0.185,"REB_PCT":0.154,"TM_TOV_PCT":21.2,"E_TOV_PCT":21.2,"EFG_PCT":0.528,"TS_PCT":0.569,"USG_PCT":0.091,"E_USG_PCT":0.093,"E_PACE":92.84,"PACE":93.63,"PACE_PER40":78.02,"sp_work_PACE":93.63,"PIE":0.079,"POSS":273,"FGM":9,"FGA":18,"FGM_PG":0.8,"FGA_PG":1.6,"FG_PCT":0.5,"GP_RANK":14,"W_RANK":14,"L_RANK":2,"W_PCT_RANK":3,"MIN_RANK":11,"E_OFF_RATING_RANK":15,"OFF_RATING_RANK":15,"sp_work_OFF_RATING_RANK":15,"E_DEF_RATING_RANK":1,"DEF_RATING_RANK":1,"sp_work_DEF_RATING_RANK":1,"E_NET_RATING_RANK":3,"NET_RATING_RANK":2,"sp_work_NET_RATING_RANK":2,"AST_PCT_RANK":13,"AST_TO_RANK":12,"AST_RATIO_RANK":9,"OREB_PCT_RANK":1,"DREB_PCT_RANK":3,"REB_PCT_RANK":2,"TM_TOV_PCT_RANK":15,"E_TOV_PCT_RANK":15,"EFG_PCT_RANK":1,"TS_PCT_RANK":1,"USG_PCT_RANK":15,"E_USG_PCT_RANK":15,"E_PACE_RANK":9,"PACE_RANK":5,"sp_work_PACE_RANK":5,"PIE_RANK":11,"FGM_RANK":14,"FGA_RANK":14,"FGM_PG_RANK":13,"FGA_PG_RANK":15,"FG_PCT_RANK":1},"8":{"GROUP_SET":"Players","PLAYER_ID":201178,"PLAYER_NAME":"Kyrylo Fesenko","GP":3,"W":3,"L":0,"W_PCT":1,"MIN":5.7,"E_OFF_RATING":118.9,"OFF_RATING":111.4,"sp_work_OFF_RATING":111.4,"E_DEF_RATING":99.4,"DEF_RATING":97,"sp_work_DEF_RATING":97,"E_NET_RATING":19.5,"NET_RATING":14.5,"sp_work_NET_RATING":14.5,"AST_PCT":0.1,"AST_TO":0,"AST_RATIO":11.1,"OREB_PCT":0.105,"DREB_PCT":0.412,"REB_PCT":0.25,"TM_TOV_PCT":0,"E_TOV_PCT":0,"EFG_PCT":0.4,"TS_PCT":0.524,"USG_PCT":0.195,"E_USG_PCT":0.202,"E_PACE":91.85,"PACE":96.09,"PACE_PER40":80.08,"sp_work_PACE":96.09,"PIE":0.214,"POSS":35,"FGM":2,"FGA":5,"FGM_PG":0.7,"FGA_PG":1.7,"FG_PCT":0.4,"GP_RANK":15,"W_RANK":15,"L_RANK":1,"W_PCT_RANK":1,"MIN_RANK":14,"E_OFF_RATING_RANK":1,"OFF_RATING_RANK":1,"sp_work_OFF_RATING_RANK":1,"E_DEF_RATING_RANK":5,"DEF_RATING_RANK":2,"sp_work_DEF_RATING_RANK":2,"E_NET_RATING_RANK":1,"NET_RATING_RANK":1,"sp_work_NET_RATING_RANK":1,"AST_PCT_RANK":9,"AST_TO_RANK":15,"AST_RATIO_RANK":10,"OREB_PCT_RANK":4,"DREB_PCT_RANK":1,"REB_PCT_RANK":1,"TM_TOV_PCT_RANK":1,"E_TOV_PCT_RANK":1,"EFG_PCT_RANK":14,"TS_PCT_RANK":9,"USG_PCT_RANK":6,"E_USG_PCT_RANK":6,"E_PACE_RANK":15,"PACE_RANK":1,"sp_work_PACE_RANK":1,"PIE_RANK":1,"FGM_RANK":15,"FGA_RANK":15,"FGM_PG_RANK":15,"FGA_PG_RANK":14,"FG_PCT_RANK":12},"9":{"GROUP_SET":"Players","PLAYER_ID":202362,"PLAYER_NAME":"Lance Stephenson","GP":42,"W":25,"L":17,"W_PCT":0.595,"MIN":10.5,"E_OFF_RATING":98.3,"OFF_RATING":98.3,"sp_work_OFF_RATING":98.3,"E_DEF_RATING":102.4,"DEF_RATING":102.2,"sp_work_DEF_RATING":102.2,"E_NET_RATING":-4,"NET_RATING":-3.9,"sp_work_NET_RATING":-3.9,"AST_PCT":0.174,"AST_TO":1.28,"AST_RATIO":21.4,"OREB_PCT":0.025,"DREB_PCT":0.098,"REB_PCT":0.059,"TM_TOV_PCT":16.7,"E_TOV_PCT":16.8,"EFG_PCT":0.392,"TS_PCT":0.4,"USG_PCT":0.166,"E_USG_PCT":0.171,"E_PACE":93.98,"PACE":94.06,"PACE_PER40":78.39,"sp_work_PACE":94.06,"PIE":0.054,"POSS":870,"FGM":47,"FGA":125,"FGM_PG":1.1,"FGA_PG":3,"FG_PCT":0.376,"GP_RANK":11,"W_RANK":11,"L_RANK":6,"W_PCT_RANK":15,"MIN_RANK":13,"E_OFF_RATING_RANK":14,"OFF_RATING_RANK":13,"sp_work_OFF_RATING_RANK":13,"E_DEF_RATING_RANK":12,"DEF_RATING_RANK":12,"sp_work_DEF_RATING_RANK":12,"E_NET_RATING_RANK":15,"NET_RATING_RANK":14,"sp_work_NET_RATING_RANK":14,"AST_PCT_RANK":4,"AST_TO_RANK":8,"AST_RATIO_RANK":4,"OREB_PCT_RANK":11,"DREB_PCT_RANK":10,"REB_PCT_RANK":10,"TM_TOV_PCT_RANK":14,"E_TOV_PCT_RANK":14,"EFG_PCT_RANK":15,"TS_PCT_RANK":15,"USG_PCT_RANK":12,"E_USG_PCT_RANK":11,"E_PACE_RANK":4,"PACE_RANK":3,"sp_work_PACE_RANK":3,"PIE_RANK":15,"FGM_RANK":12,"FGA_RANK":12,"FGM_PG_RANK":12,"FGA_PG_RANK":12,"FG_PCT_RANK":14},"10":{"GROUP_SET":"Players","PLAYER_ID":2571,"PLAYER_NAME":"Leandro Barbosa","GP":22,"W":17,"L":5,"W_PCT":0.773,"MIN":19.8,"E_OFF_RATING":105.4,"OFF_RATING":104.6,"sp_work_OFF_RATING":104.6,"E_DEF_RATING":105.1,"DEF_RATING":104,"sp_work_DEF_RATING":104,"E_NET_RATING":0.3,"NET_RATING":0.6,"sp_work_NET_RATING":0.6,"AST_PCT":0.143,"AST_TO":1.27,"AST_RATIO":12.9,"OREB_PCT":0.026,"DREB_PCT":0.086,"REB_PCT":0.055,"TM_TOV_PCT":10.2,"E_TOV_PCT":10.1,"EFG_PCT":0.467,"TS_PCT":0.496,"USG_PCT":0.219,"E_USG_PCT":0.228,"E_PACE":92.73,"PACE":93.6,"PACE_PER40":78,"sp_work_PACE":93.6,"PIE":0.089,"POSS":851,"FGM":73,"FGA":183,"FGM_PG":3.3,"FGA_PG":8.3,"FG_PCT":0.399,"GP_RANK":12,"W_RANK":12,"L_RANK":3,"W_PCT_RANK":2,"MIN_RANK":8,"E_OFF_RATING_RANK":5,"OFF_RATING_RANK":9,"sp_work_OFF_RATING_RANK":9,"E_DEF_RATING_RANK":14,"DEF_RATING_RANK":15,"sp_work_DEF_RATING_RANK":15,"E_NET_RATING_RANK":10,"NET_RATING_RANK":11,"sp_work_NET_RATING_RANK":11,"AST_PCT_RANK":5,"AST_TO_RANK":9,"AST_RATIO_RANK":8,"OREB_PCT_RANK":10,"DREB_PCT_RANK":14,"REB_PCT_RANK":13,"TM_TOV_PCT_RANK":7,"E_TOV_PCT_RANK":7,"EFG_PCT_RANK":9,"TS_PCT_RANK":11,"USG_PCT_RANK":2,"E_USG_PCT_RANK":2,"E_PACE_RANK":10,"PACE_RANK":6,"sp_work_PACE_RANK":6,"PIE_RANK":10,"FGM_RANK":10,"FGA_RANK":10,"FGM_PG_RANK":7,"FGA_PG_RANK":6,"FG_PCT_RANK":13},"11":{"GROUP_SET":"Players","PLAYER_ID":200811,"PLAYER_NAME":"Lou Amundson","GP":60,"W":38,"L":22,"W_PCT":0.633,"MIN":12.5,"E_OFF_RATING":98.7,"OFF_RATING":98.2,"sp_work_OFF_RATING":98.2,"E_DEF_RATING":101.8,"DEF_RATING":100.9,"sp_work_DEF_RATING":100.9,"E_NET_RATING":-3.2,"NET_RATING":-2.7,"sp_work_NET_RATING":-2.7,"AST_PCT":0.033,"AST_TO":0.31,"AST_RATIO":4.6,"OREB_PCT":0.116,"DREB_PCT":0.175,"REB_PCT":0.144,"TM_TOV_PCT":14.9,"E_TOV_PCT":14.9,"EFG_PCT":0.43,"TS_PCT":0.438,"USG_PCT":0.166,"E_USG_PCT":0.171,"E_PACE":93.21,"PACE":93.88,"PACE_PER40":78.24,"sp_work_PACE":93.88,"PIE":0.058,"POSS":1475,"FGM":89,"FGA":207,"FGM_PG":1.5,"FGA_PG":3.5,"FG_PCT":0.43,"GP_RANK":7,"W_RANK":7,"L_RANK":9,"W_PCT_RANK":11,"MIN_RANK":12,"E_OFF_RATING_RANK":13,"OFF_RATING_RANK":14,"sp_work_OFF_RATING_RANK":14,"E_DEF_RATING_RANK":11,"DEF_RATING_RANK":7,"sp_work_DEF_RATING_RANK":7,"E_NET_RATING_RANK":13,"NET_RATING_RANK":13,"sp_work_NET_RATING_RANK":13,"AST_PCT_RANK":15,"AST_TO_RANK":14,"AST_RATIO_RANK":14,"OREB_PCT_RANK":2,"DREB_PCT_RANK":5,"REB_PCT_RANK":5,"TM_TOV_PCT_RANK":13,"E_TOV_PCT_RANK":13,"EFG_PCT_RANK":10,"TS_PCT_RANK":13,"USG_PCT_RANK":11,"E_USG_PCT_RANK":10,"E_PACE_RANK":7,"PACE_RANK":4,"sp_work_PACE_RANK":4,"PIE_RANK":14,"FGM_RANK":9,"FGA_RANK":9,"FGM_PG_RANK":10,"FGA_PG_RANK":11,"FG_PCT_RANK":7},"12":{"GROUP_SET":"Players","PLAYER_ID":202331,"PLAYER_NAME":"Paul George","GP":66,"W":42,"L":24,"W_PCT":0.636,"MIN":29.7,"E_OFF_RATING":104.3,"OFF_RATING":105.5,"sp_work_OFF_RATING":105.5,"E_DEF_RATING":98.3,"DEF_RATING":99.1,"sp_work_DEF_RATING":99.1,"E_NET_RATING":6.1,"NET_RATING":6.4,"sp_work_NET_RATING":6.4,"AST_PCT":0.133,"AST_TO":1.35,"AST_RATIO":15.8,"OREB_PCT":0.029,"DREB_PCT":0.157,"REB_PCT":0.094,"TM_TOV_PCT":11.7,"E_TOV_PCT":11.8,"EFG_PCT":0.51,"TS_PCT":0.555,"USG_PCT":0.191,"E_USG_PCT":0.193,"E_PACE":94.11,"PACE":93.23,"PACE_PER40":77.69,"sp_work_PACE":93.23,"PIE":0.118,"POSS":3803,"FGM":281,"FGA":639,"FGM_PG":4.3,"FGA_PG":9.7,"FG_PCT":0.44,"GP_RANK":1,"W_RANK":1,"L_RANK":11,"W_PCT_RANK":8,"MIN_RANK":4,"E_OFF_RATING_RANK":8,"OFF_RATING_RANK":7,"sp_work_OFF_RATING_RANK":7,"E_DEF_RATING_RANK":2,"DEF_RATING_RANK":4,"sp_work_DEF_RATING_RANK":4,"E_NET_RATING_RANK":4,"NET_RATING_RANK":4,"sp_work_NET_RATING_RANK":4,"AST_PCT_RANK":6,"AST_TO_RANK":7,"AST_RATIO_RANK":5,"OREB_PCT_RANK":9,"DREB_PCT_RANK":7,"REB_PCT_RANK":8,"TM_TOV_PCT_RANK":11,"E_TOV_PCT_RANK":11,"EFG_PCT_RANK":3,"TS_PCT_RANK":3,"USG_PCT_RANK":7,"E_USG_PCT_RANK":7,"E_PACE_RANK":1,"PACE_RANK":8,"sp_work_PACE_RANK":8,"PIE_RANK":4,"FGM_RANK":4,"FGA_RANK":4,"FGM_PG_RANK":4,"FGA_PG_RANK":4,"FG_PCT_RANK":6},"13":{"GROUP_SET":"Players","PLAYER_ID":201579,"PLAYER_NAME":"Roy Hibbert","GP":65,"W":41,"L":24,"W_PCT":0.631,"MIN":29.8,"E_OFF_RATING":105.6,"OFF_RATING":106.7,"sp_work_OFF_RATING":106.7,"E_DEF_RATING":100.2,"DEF_RATING":101.4,"sp_work_DEF_RATING":101.4,"E_NET_RATING":5.4,"NET_RATING":5.3,"sp_work_NET_RATING":5.3,"AST_PCT":0.093,"AST_TO":0.84,"AST_RATIO":10.7,"OREB_PCT":0.114,"DREB_PCT":0.183,"REB_PCT":0.15,"TM_TOV_PCT":12.7,"E_TOV_PCT":12.7,"EFG_PCT":0.497,"TS_PCT":0.539,"USG_PCT":0.209,"E_USG_PCT":0.212,"E_PACE":93.5,"PACE":92.42,"PACE_PER40":77.02,"sp_work_PACE":92.42,"PIE":0.122,"POSS":3738,"FGM":332,"FGA":668,"FGM_PG":5.1,"FGA_PG":10.3,"FG_PCT":0.497,"GP_RANK":4,"W_RANK":5,"L_RANK":11,"W_PCT_RANK":12,"MIN_RANK":3,"E_OFF_RATING_RANK":4,"OFF_RATING_RANK":3,"sp_work_OFF_RATING_RANK":3,"E_DEF_RATING_RANK":7,"DEF_RATING_RANK":9,"sp_work_DEF_RATING_RANK":9,"E_NET_RATING_RANK":5,"NET_RATING_RANK":6,"sp_work_NET_RATING_RANK":6,"AST_PCT_RANK":10,"AST_TO_RANK":11,"AST_RATIO_RANK":11,"OREB_PCT_RANK":3,"DREB_PCT_RANK":4,"REB_PCT_RANK":3,"TM_TOV_PCT_RANK":12,"E_TOV_PCT_RANK":12,"EFG_PCT_RANK":4,"TS_PCT_RANK":5,"USG_PCT_RANK":3,"E_USG_PCT_RANK":4,"E_PACE_RANK":6,"PACE_RANK":13,"sp_work_PACE_RANK":13,"PIE_RANK":3,"FGM_RANK":3,"FGA_RANK":3,"FGM_PG_RANK":3,"FGA_PG_RANK":3,"FG_PCT_RANK":2},"14":{"GROUP_SET":"Players","PLAYER_ID":201946,"PLAYER_NAME":"Tyler Hansbrough","GP":66,"W":42,"L":24,"W_PCT":0.636,"MIN":21.8,"E_OFF_RATING":100.3,"OFF_RATING":101.1,"sp_work_OFF_RATING":101.1,"E_DEF_RATING":101.8,"DEF_RATING":101.4,"sp_work_DEF_RATING":101.4,"E_NET_RATING":-1.5,"NET_RATING":-0.4,"sp_work_NET_RATING":-0.4,"AST_PCT":0.038,"AST_TO":0.46,"AST_RATIO":4.3,"OREB_PCT":0.076,"DREB_PCT":0.127,"REB_PCT":0.101,"TM_TOV_PCT":9.3,"E_TOV_PCT":9.3,"EFG_PCT":0.405,"TS_PCT":0.511,"USG_PCT":0.208,"E_USG_PCT":0.212,"E_PACE":92.2,"PACE":92.06,"PACE_PER40":76.72,"sp_work_PACE":92.06,"PIE":0.093,"POSS":2758,"FGM":194,"FGA":479,"FGM_PG":2.9,"FGA_PG":7.3,"FG_PCT":0.405,"GP_RANK":1,"W_RANK":1,"L_RANK":11,"W_PCT_RANK":8,"MIN_RANK":7,"E_OFF_RATING_RANK":10,"OFF_RATING_RANK":10,"sp_work_OFF_RATING_RANK":10,"E_DEF_RATING_RANK":10,"DEF_RATING_RANK":8,"sp_work_DEF_RATING_RANK":8,"E_NET_RATING_RANK":12,"NET_RATING_RANK":12,"sp_work_NET_RATING_RANK":12,"AST_PCT_RANK":14,"AST_TO_RANK":13,"AST_RATIO_RANK":15,"OREB_PCT_RANK":6,"DREB_PCT_RANK":8,"REB_PCT_RANK":7,"TM_TOV_PCT_RANK":6,"E_TOV_PCT_RANK":6,"EFG_PCT_RANK":13,"TS_PCT_RANK":10,"USG_PCT_RANK":4,"E_USG_PCT_RANK":3,"E_PACE_RANK":12,"PACE_RANK":14,"sp_work_PACE_RANK":14,"PIE_RANK":9,"FGM_RANK":6,"FGA_RANK":6,"FGM_PG_RANK":8,"FGA_PG_RANK":8,"FG_PCT_RANK":11}}}