{"TeamOverall":{"GROUP_SET":"Overall","TEAM_ID":1610612739,"TEAM_NAME":"Cleveland Cavaliers","GROUP_VALUE":"2012-13","GP":82,"W":24,"L":58,"W_PCT":0.293,"MIN":3946,"E_OFF_RATING":100.8,"OFF_RATING":103.2,"E_DEF_RATING":106.9,"DEF_RATING":108.2,"E_NET_RATING":-6.1,"NET_RATING":-5,"AST_PCT":0.566,"AST_TO":1.47,"AST_RATIO":15.9,"OREB_PCT":0.326,"DREB_PCT":0.695,"REB_PCT":0.5,"TM_TOV_PCT":0.15,"EFG_PCT":0.473,"TS_PCT":0.514,"E_PACE":94.9,"PACE":93.25,"PACE_PER40":77.71,"POSS":7666,"PIE":0.45,"GP_RANK":1,"W_RANK":1,"L_RANK":1,"W_PCT_RANK":1,"MIN_RANK":1,"OFF_RATING_RANK":1,"DEF_RATING_RANK":1,"NET_RATING_RANK":1,"AST_PCT_RANK":1,"AST_TO_RANK":1,"AST_RATIO_RANK":1,"OREB_PCT_RANK":1,"DREB_PCT_RANK":1,"REB_PCT_RANK":1,"TM_TOV_PCT_RANK":1,"EFG_PCT_RANK":1,"TS_PCT_RANK":1,"PACE_RANK":1,"PIE_RANK":1},"PlayersSeasonTotals":{"0":{"GROUP_SET":"Players","PLAYER_ID":202087,"PLAYER_NAME":"Alonzo Gee","GP":82,"W":24,"L":58,"W_PCT":0.293,"MIN":31,"E_OFF_RATING":101.1,"OFF_RATING":102.7,"sp_work_OFF_RATING":102.7,"E_DEF_RATING":109.1,"DEF_RATING":109.7,"sp_work_DEF_RATING":109.7,"E_NET_RATING":-8,"NET_RATING":-7,"sp_work_NET_RATING":-7,"AST_PCT":0.081,"AST_TO":1.01,"AST_RATIO":12,"OREB_PCT":0.028,"DREB_PCT":0.105,"REB_PCT":0.064,"TM_TOV_PCT":12,"E_TOV_PCT":12,"EFG_PCT":0.456,"TS_PCT":0.505,"USG_PCT":0.166,"E_USG_PCT":0.168,"E_PACE":95.6,"PACE":94.58,"PACE_PER40":78.82,"sp_work_PACE":94.58,"PIE":0.064,"POSS":5006,"FGM":305,"FGA":744,"FGM_PG":3.7,"FGA_PG":9.1,"FG_PCT":0.41,"GP_RANK":1,"W_RANK":1,"L_RANK":18,"W_PCT_RANK":8,"MIN_RANK":4,"E_OFF_RATING_RANK":9,"OFF_RATING_RANK":8,"sp_work_OFF_RATING_RANK":8,"E_DEF_RATING_RANK":17,"DEF_RATING_RANK":18,"sp_work_DEF_RATING_RANK":18,"E_NET_RATING_RANK":13,"NET_RATING_RANK":16,"sp_work_NET_RATING_RANK":16,"AST_PCT_RANK":14,"AST_TO_RANK":15,"AST_RATIO_RANK":13,"OREB_PCT_RANK":10,"DREB_PCT_RANK":11,"REB_PCT_RANK":11,"TM_TOV_PCT_RANK":15,"E_TOV_PCT_RANK":15,"EFG_PCT_RANK":9,"TS_PCT_RANK":8,"USG_PCT_RANK":13,"E_USG_PCT_RANK":13,"E_PACE_RANK":5,"PACE_RANK":7,"sp_work_PACE_RANK":7,"PIE_RANK":14,"FGM_RANK":4,"FGA_RANK":4,"FGM_PG_RANK":8,"FGA_PG_RANK":6,"FG_PCT_RANK":10},"1":{"GROUP_SET":"Players","PLAYER_ID":2760,"PLAYER_NAME":"Anderson Varejao","GP":25,"W":5,"L":20,"W_PCT":0.2,"MIN":36,"E_OFF_RATING":100.1,"OFF_RATING":103.4,"sp_work_OFF_RATING":103.4,"E_DEF_RATING":107.4,"DEF_RATING":107.3,"sp_work_DEF_RATING":107.3,"E_NET_RATING":-7.3,"NET_RATING":-4,"sp_work_NET_RATING":-4,"AST_PCT":0.157,"AST_TO":1.91,"AST_RATIO":18.2,"OREB_PCT":0.141,"DREB_PCT":0.272,"REB_PCT":0.2,"TM_TOV_PCT":9.5,"E_TOV_PCT":9.5,"EFG_PCT":0.478,"TS_PCT":0.529,"USG_PCT":0.178,"E_USG_PCT":0.18,"E_PACE":95.05,"PACE":93.53,"PACE_PER40":77.94,"sp_work_PACE":93.53,"PIE":0.164,"POSS":1753,"FGM":138,"FGA":289,"FGM_PG":5.5,"FGA_PG":11.6,"FG_PCT":0.478,"GP_RANK":14,"W_RANK":14,"L_RANK":6,"W_PCT_RANK":14,"MIN_RANK":1,"E_OFF_RATING_RANK":11,"OFF_RATING_RANK":6,"sp_work_OFF_RATING_RANK":6,"E_DEF_RATING_RANK":14,"DEF_RATING_RANK":12,"sp_work_DEF_RATING_RANK":12,"E_NET_RATING_RANK":12,"NET_RATING_RANK":8,"sp_work_NET_RATING_RANK":8,"AST_PCT_RANK":7,"AST_TO_RANK":5,"AST_RATIO_RANK":8,"OREB_PCT_RANK":1,"DREB_PCT_RANK":1,"REB_PCT_RANK":1,"TM_TOV_PCT_RANK":7,"E_TOV_PCT_RANK":7,"EFG_PCT_RANK":6,"TS_PCT_RANK":5,"USG_PCT_RANK":7,"E_USG_PCT_RANK":7,"E_PACE_RANK":7,"PACE_RANK":14,"sp_work_PACE_RANK":14,"PIE_RANK":1,"FGM_RANK":10,"FGA_RANK":9,"FGM_PG_RANK":2,"FGA_PG_RANK":3,"FG_PCT_RANK":3},"2":{"GROUP_SET":"Players","PLAYER_ID":101139,"PLAYER_NAME":"CJ Miles","GP":65,"W":19,"L":46,"W_PCT":0.292,"MIN":21,"E_OFF_RATING":101.2,"OFF_RATING":102.2,"sp_work_OFF_RATING":102.2,"E_DEF_RATING":105.2,"DEF_RATING":105.5,"sp_work_DEF_RATING":105.5,"E_NET_RATING":-4.1,"NET_RATING":-3.3,"sp_work_NET_RATING":-3.3,"AST_PCT":0.083,"AST_TO":0.91,"AST_RATIO":8,"OREB_PCT":0.017,"DREB_PCT":0.114,"REB_PCT":0.064,"TM_TOV_PCT":8.8,"E_TOV_PCT":8.7,"EFG_PCT":0.518,"TS_PCT":0.551,"USG_PCT":0.234,"E_USG_PCT":0.24,"E_PACE":95.34,"PACE":94.7,"PACE_PER40":78.92,"sp_work_PACE":94.7,"PIE":0.096,"POSS":2693,"FGM":255,"FGA":614,"FGM_PG":3.9,"FGA_PG":9.4,"FG_PCT":0.415,"GP_RANK":4,"W_RANK":5,"L_RANK":16,"W_PCT_RANK":10,"MIN_RANK":9,"E_OFF_RATING_RANK":8,"OFF_RATING_RANK":10,"sp_work_OFF_RATING_RANK":10,"E_DEF_RATING_RANK":7,"DEF_RATING_RANK":8,"sp_work_DEF_RATING_RANK":8,"E_NET_RATING_RANK":6,"NET_RATING_RANK":7,"sp_work_NET_RATING_RANK":7,"AST_PCT_RANK":13,"AST_TO_RANK":17,"AST_RATIO_RANK":17,"OREB_PCT_RANK":13,"DREB_PCT_RANK":8,"REB_PCT_RANK":10,"TM_TOV_PCT_RANK":5,"E_TOV_PCT_RANK":5,"EFG_PCT_RANK":2,"TS_PCT_RANK":4,"USG_PCT_RANK":5,"E_USG_PCT_RANK":5,"E_PACE_RANK":6,"PACE_RANK":6,"sp_work_PACE_RANK":6,"PIE_RANK":6,"FGM_RANK":5,"FGA_RANK":5,"FGM_PG_RANK":6,"FGA_PG_RANK":5,"FG_PCT_RANK":8},"3":{"GROUP_SET":"Players","PLAYER_ID":200809,"PLAYER_NAME":"Chris Quinn","GP":7,"W":0,"L":7,"W_PCT":0,"MIN":11.2,"E_OFF_RATING":93.6,"OFF_RATING":97.4,"sp_work_OFF_RATING":97.4,"E_DEF_RATING":89.9,"DEF_RATING":89.5,"sp_work_DEF_RATING":89.5,"E_NET_RATING":3.7,"NET_RATING":7.9,"sp_work_NET_RATING":7.9,"AST_PCT":0.155,"AST_TO":1.5,"AST_RATIO":28.1,"OREB_PCT":0.013,"DREB_PCT":0.015,"REB_PCT":0.014,"TM_TOV_PCT":18.8,"E_TOV_PCT":18.8,"EFG_PCT":0.25,"TS_PCT":0.296,"USG_PCT":0.131,"E_USG_PCT":0.132,"E_PACE":94.44,"PACE":92.83,"PACE_PER40":77.36,"sp_work_PACE":92.83,"PIE":0.006,"POSS":151,"FGM":4,"FGA":16,"FGM_PG":0.6,"FGA_PG":2.3,"FG_PCT":0.25,"GP_RANK":19,"W_RANK":19,"L_RANK":1,"W_PCT_RANK":19,"MIN_RANK":16,"E_OFF_RATING_RANK":17,"OFF_RATING_RANK":14,"sp_work_OFF_RATING_RANK":14,"E_DEF_RATING_RANK":1,"DEF_RATING_RANK":1,"sp_work_DEF_RATING_RANK":1,"E_NET_RATING_RANK":2,"NET_RATING_RANK":2,"sp_work_NET_RATING_RANK":2,"AST_PCT_RANK":8,"AST_TO_RANK":10,"AST_RATIO_RANK":3,"OREB_PCT_RANK":16,"DREB_PCT_RANK":19,"REB_PCT_RANK":19,"TM_TOV_PCT_RANK":19,"E_TOV_PCT_RANK":19,"EFG_PCT_RANK":19,"TS_PCT_RANK":19,"USG_PCT_RANK":19,"E_USG_PCT_RANK":19,"E_PACE_RANK":14,"PACE_RANK":18,"sp_work_PACE_RANK":18,"PIE_RANK":18,"FGM_RANK":19,"FGA_RANK":19,"FGM_PG_RANK":19,"FGA_PG_RANK":19,"FG_PCT_RANK":19},"4":{"GROUP_SET":"Players","PLAYER_ID":200789,"PLAYER_NAME":"Daniel Gibson","GP":46,"W":11,"L":35,"W_PCT":0.239,"MIN":20,"E_OFF_RATING":94.5,"OFF_RATING":95.9,"sp_work_OFF_RATING":95.9,"E_DEF_RATING":108,"DEF_RATING":107.4,"sp_work_DEF_RATING":107.4,"E_NET_RATING":-13.5,"NET_RATING":-11.5,"sp_work_NET_RATING":-11.5,"AST_PCT":0.147,"AST_TO":2.65,"AST_RATIO":21.9,"OREB_PCT":0.005,"DREB_PCT":0.067,"REB_PCT":0.034,"TM_TOV_PCT":8.3,"E_TOV_PCT":8.2,"EFG_PCT":0.453,"TS_PCT":0.475,"USG_PCT":0.14,"E_USG_PCT":0.144,"E_PACE":94.03,"PACE":93.61,"PACE_PER40":78.01,"sp_work_PACE":93.61,"PIE":0.044,"POSS":1794,"FGM":84,"FGA":247,"FGM_PG":1.8,"FGA_PG":5.4,"FG_PCT":0.34,"GP_RANK":9,"W_RANK":11,"L_RANK":13,"W_PCT_RANK":12,"MIN_RANK":10,"E_OFF_RATING_RANK":15,"OFF_RATING_RANK":16,"sp_work_OFF_RATING_RANK":16,"E_DEF_RATING_RANK":16,"DEF_RATING_RANK":13,"sp_work_DEF_RATING_RANK":13,"E_NET_RATING_RANK":17,"NET_RATING_RANK":17,"sp_work_NET_RATING_RANK":17,"AST_PCT_RANK":9,"AST_TO_RANK":4,"AST_RATIO_RANK":5,"OREB_PCT_RANK":19,"DREB_PCT_RANK":17,"REB_PCT_RANK":18,"TM_TOV_PCT_RANK":4,"E_TOV_PCT_RANK":4,"EFG_PCT_RANK":10,"TS_PCT_RANK":13,"USG_PCT_RANK":17,"E_USG_PCT_RANK":17,"E_PACE_RANK":15,"PACE_RANK":12,"sp_work_PACE_RANK":12,"PIE_RANK":16,"FGM_RANK":11,"FGA_RANK":11,"FGM_PG_RANK":12,"FGA_PG_RANK":12,"FG_PCT_RANK":18},"5":{"GROUP_SET":"Players","PLAYER_ID":203079,"PLAYER_NAME":"Dion Waiters","GP":61,"W":20,"L":41,"W_PCT":0.328,"MIN":28.8,"E_OFF_RATING":103.3,"OFF_RATING":105.4,"sp_work_OFF_RATING":105.4,"E_DEF_RATING":109.6,"DEF_RATING":109.8,"sp_work_DEF_RATING":109.8,"E_NET_RATING":-6.3,"NET_RATING":-4.3,"sp_work_NET_RATING":-4.3,"AST_PCT":0.178,"AST_TO":1.51,"AST_RATIO":15,"OREB_PCT":0.012,"DREB_PCT":0.081,"REB_PCT":0.044,"TM_TOV_PCT":10,"E_TOV_PCT":10,"EFG_PCT":0.451,"TS_PCT":0.492,"USG_PCT":0.258,"E_USG_PCT":0.261,"E_PACE":94.52,"PACE":93.51,"PACE_PER40":77.92,"sp_work_PACE":93.51,"PIE":0.083,"POSS":3419,"FGM":336,"FGA":815,"FGM_PG":5.5,"FGA_PG":13.4,"FG_PCT":0.412,"GP_RANK":5,"W_RANK":4,"L_RANK":15,"W_PCT_RANK":4,"MIN_RANK":5,"E_OFF_RATING_RANK":4,"OFF_RATING_RANK":2,"sp_work_OFF_RATING_RANK":2,"E_DEF_RATING_RANK":18,"DEF_RATING_RANK":19,"sp_work_DEF_RATING_RANK":19,"E_NET_RATING_RANK":10,"NET_RATING_RANK":9,"sp_work_NET_RATING_RANK":9,"AST_PCT_RANK":6,"AST_TO_RANK":9,"AST_RATIO_RANK":9,"OREB_PCT_RANK":17,"DREB_PCT_RANK":16,"REB_PCT_RANK":16,"TM_TOV_PCT_RANK":10,"E_TOV_PCT_RANK":10,"EFG_PCT_RANK":11,"TS_PCT_RANK":9,"USG_PCT_RANK":3,"E_USG_PCT_RANK":3,"E_PACE_RANK":12,"PACE_RANK":15,"sp_work_PACE_RANK":15,"PIE_RANK":10,"FGM_RANK":3,"FGA_RANK":2,"FGM_PG_RANK":3,"FGA_PG_RANK":2,"FG_PCT_RANK":9},"6":{"GROUP_SET":"Players","PLAYER_ID":202388,"PLAYER_NAME":"Donald Sloan","GP":20,"W":3,"L":17,"W_PCT":0.15,"MIN":12.8,"E_OFF_RATING":87.6,"OFF_RATING":87.8,"sp_work_OFF_RATING":87.8,"E_DEF_RATING":103,"DEF_RATING":100,"sp_work_DEF_RATING":100,"E_NET_RATING":-15.4,"NET_RATING":-12.2,"sp_work_NET_RATING":-12.2,"AST_PCT":0.28,"AST_TO":2.85,"AST_RATIO":26.6,"OREB_PCT":0.01,"DREB_PCT":0.099,"REB_PCT":0.052,"TM_TOV_PCT":9.4,"E_TOV_PCT":9.4,"EFG_PCT":0.391,"TS_PCT":0.455,"USG_PCT":0.174,"E_USG_PCT":0.18,"E_PACE":92.17,"PACE":93.44,"PACE_PER40":77.86,"sp_work_PACE":93.44,"PIE":0.092,"POSS":500,"FGM":27,"FGA":78,"FGM_PG":1.4,"FGA_PG":3.9,"FG_PCT":0.346,"GP_RANK":16,"W_RANK":16,"L_RANK":4,"W_PCT_RANK":17,"MIN_RANK":14,"E_OFF_RATING_RANK":18,"OFF_RATING_RANK":18,"sp_work_OFF_RATING_RANK":18,"E_DEF_RATING_RANK":4,"DEF_RATING_RANK":4,"sp_work_DEF_RATING_RANK":4,"E_NET_RATING_RANK":18,"NET_RATING_RANK":18,"sp_work_NET_RATING_RANK":18,"AST_PCT_RANK":3,"AST_TO_RANK":2,"AST_RATIO_RANK":4,"OREB_PCT_RANK":18,"DREB_PCT_RANK":12,"REB_PCT_RANK":15,"TM_TOV_PCT_RANK":6,"E_TOV_PCT_RANK":6,"EFG_PCT_RANK":16,"TS_PCT_RANK":14,"USG_PCT_RANK":9,"E_USG_PCT_RANK":8,"E_PACE_RANK":19,"PACE_RANK":16,"sp_work_PACE_RANK":16,"PIE_RANK":9,"FGM_RANK":16,"FGA_RANK":16,"FGM_PG_RANK":15,"FGA_PG_RANK":13,"FG_PCT_RANK":17},"7":{"GROUP_SET":"Players","PLAYER_ID":202951,"PLAYER_NAME":"Jeremy Pargo","GP":25,"W":6,"L":19,"W_PCT":0.24,"MIN":17.9,"E_OFF_RATING":95.4,"OFF_RATING":98.7,"sp_work_OFF_RATING":98.7,"E_DEF_RATING":104,"DEF_RATING":103.3,"sp_work_DEF_RATING":103.3,"E_NET_RATING":-8.7,"NET_RATING":-4.6,"sp_work_NET_RATING":-4.6,"AST_PCT":0.264,"AST_TO":1.73,"AST_RATIO":20.8,"OREB_PCT":0.014,"DREB_PCT":0.06,"REB_PCT":0.035,"TM_TOV_PCT":12.1,"E_TOV_PCT":12.1,"EFG_PCT":0.449,"TS_PCT":0.478,"USG_PCT":0.24,"E_USG_PCT":0.242,"E_PACE":92.79,"PACE":91.54,"PACE_PER40":76.29,"sp_work_PACE":91.54,"PIE":0.079,"POSS":849,"FGM":75,"FGA":187,"FGM_PG":3,"FGA_PG":7.5,"FG_PCT":0.401,"GP_RANK":14,"W_RANK":13,"L_RANK":5,"W_PCT_RANK":11,"MIN_RANK":12,"E_OFF_RATING_RANK":13,"OFF_RATING_RANK":13,"sp_work_OFF_RATING_RANK":13,"E_DEF_RATING_RANK":5,"DEF_RATING_RANK":6,"sp_work_DEF_RATING_RANK":6,"E_NET_RATING_RANK":15,"NET_RATING_RANK":10,"sp_work_NET_RATING_RANK":10,"AST_PCT_RANK":4,"AST_TO_RANK":8,"AST_RATIO_RANK":6,"OREB_PCT_RANK":15,"DREB_PCT_RANK":18,"REB_PCT_RANK":17,"TM_TOV_PCT_RANK":16,"E_TOV_PCT_RANK":16,"EFG_PCT_RANK":12,"TS_PCT_RANK":12,"USG_PCT_RANK":4,"E_USG_PCT_RANK":4,"E_PACE_RANK":18,"PACE_RANK":19,"sp_work_PACE_RANK":19,"PIE_RANK":12,"FGM_RANK":12,"FGA_RANK":12,"FGM_PG_RANK":10,"FGA_PG_RANK":9,"FG_PCT_RANK":12},"8":{"GROUP_SET":"Players","PLAYER_ID":202720,"PLAYER_NAME":"Jon Leuer","GP":9,"W":1,"L":8,"W_PCT":0.111,"MIN":10.1,"E_OFF_RATING":86.7,"OFF_RATING":84.8,"sp_work_OFF_RATING":84.8,"E_DEF_RATING":111.9,"DEF_RATING":108,"sp_work_DEF_RATING":108,"E_NET_RATING":-25.2,"NET_RATING":-23.2,"sp_work_NET_RATING":-23.2,"AST_PCT":0.098,"AST_TO":1,"AST_RATIO":12.2,"OREB_PCT":0.05,"DREB_PCT":0.11,"REB_PCT":0.075,"TM_TOV_PCT":12.2,"E_TOV_PCT":12.3,"EFG_PCT":0.357,"TS_PCT":0.359,"USG_PCT":0.171,"E_USG_PCT":0.175,"E_PACE":96.86,"PACE":99.66,"PACE_PER40":83.05,"sp_work_PACE":99.66,"PIE":0.005,"POSS":191,"FGM":10,"FGA":28,"FGM_PG":1.1,"FGA_PG":3.1,"FG_PCT":0.357,"GP_RANK":18,"W_RANK":18,"L_RANK":2,"W_PCT_RANK":18,"MIN_RANK":19,"E_OFF_RATING_RANK":19,"OFF_RATING_RANK":19,"sp_work_OFF_RATING_RANK":19,"E_DEF_RATING_RANK":19,"DEF_RATING_RANK":15,"sp_work_DEF_RATING_RANK":15,"E_NET_RATING_RANK":19,"NET_RATING_RANK":19,"sp_work_NET_RATING_RANK":19,"AST_PCT_RANK":11,"AST_TO_RANK":16,"AST_RATIO_RANK":11,"OREB_PCT_RANK":6,"DREB_PCT_RANK":9,"REB_PCT_RANK":8,"TM_TOV_PCT_RANK":17,"E_TOV_PCT_RANK":17,"EFG_PCT_RANK":18,"TS_PCT_RANK":18,"USG_PCT_RANK":12,"E_USG_PCT_RANK":11,"E_PACE_RANK":1,"PACE_RANK":1,"sp_work_PACE_RANK":1,"PIE_RANK":19,"FGM_RANK":18,"FGA_RANK":18,"FGM_PG_RANK":18,"FGA_PG_RANK":18,"FG_PCT_RANK":16},"9":{"GROUP_SET":"Players","PLAYER_ID":203158,"PLAYER_NAME":"Kevin Jones","GP":32,"W":5,"L":27,"W_PCT":0.156,"MIN":10.4,"E_OFF_RATING":106.9,"OFF_RATING":107.9,"sp_work_OFF_RATING":107.9,"E_DEF_RATING":100.9,"DEF_RATING":98.7,"sp_work_DEF_RATING":98.7,"E_NET_RATING":6,"NET_RATING":9.2,"sp_work_NET_RATING":9.2,"AST_PCT":0.043,"AST_TO":1.25,"AST_RATIO":7.6,"OREB_PCT":0.107,"DREB_PCT":0.127,"REB_PCT":0.116,"TM_TOV_PCT":6.1,"E_TOV_PCT":6.1,"EFG_PCT":0.402,"TS_PCT":0.418,"USG_PCT":0.155,"E_USG_PCT":0.158,"E_PACE":94.82,"PACE":95.42,"PACE_PER40":79.52,"sp_work_PACE":95.42,"PIE":0.063,"POSS":661,"FGM":43,"FGA":107,"FGM_PG":1.3,"FGA_PG":3.3,"FG_PCT":0.402,"GP_RANK":13,"W_RANK":14,"L_RANK":9,"W_PCT_RANK":16,"MIN_RANK":18,"E_OFF_RATING_RANK":1,"OFF_RATING_RANK":1,"sp_work_OFF_RATING_RANK":1,"E_DEF_RATING_RANK":3,"DEF_RATING_RANK":2,"sp_work_DEF_RATING_RANK":2,"E_NET_RATING_RANK":1,"NET_RATING_RANK":1,"sp_work_NET_RATING_RANK":1,"AST_PCT_RANK":19,"AST_TO_RANK":13,"AST_RATIO_RANK":18,"OREB_PCT_RANK":3,"DREB_PCT_RANK":7,"REB_PCT_RANK":4,"TM_TOV_PCT_RANK":1,"E_TOV_PCT_RANK":1,"EFG_PCT_RANK":15,"TS_PCT_RANK":16,"USG_PCT_RANK":15,"E_USG_PCT_RANK":15,"E_PACE_RANK":9,"PACE_RANK":4,"sp_work_PACE_RANK":4,"PIE_RANK":15,"FGM_RANK":15,"FGA_RANK":15,"FGM_PG_RANK":16,"FGA_PG_RANK":16,"FG_PCT_RANK":11},"10":{"GROUP_SET":"Players","PLAYER_ID":202681,"PLAYER_NAME":"Kyrie Irving","GP":59,"W":19,"L":40,"W_PCT":0.322,"MIN":34.7,"E_OFF_RATING":102.6,"OFF_RATING":104,"sp_work_OFF_RATING":104,"E_DEF_RATING":107.7,"DEF_RATING":108.7,"sp_work_DEF_RATING":108.7,"E_NET_RATING":-5.1,"NET_RATING":-4.6,"sp_work_NET_RATING":-4.6,"AST_PCT":0.315,"AST_TO":1.83,"AST_RATIO":20.3,"OREB_PCT":0.016,"DREB_PCT":0.095,"REB_PCT":0.053,"TM_TOV_PCT":11.1,"E_TOV_PCT":11,"EFG_PCT":0.503,"TS_PCT":0.553,"USG_PCT":0.292,"E_USG_PCT":0.298,"E_PACE":96.55,"PACE":95.48,"PACE_PER40":79.57,"sp_work_PACE":95.48,"PIE":0.139,"POSS":4079,"FGM":484,"FGA":1070,"FGM_PG":8.2,"FGA_PG":18.1,"FG_PCT":0.452,"GP_RANK":6,"W_RANK":5,"L_RANK":14,"W_PCT_RANK":5,"MIN_RANK":2,"E_OFF_RATING_RANK":6,"OFF_RATING_RANK":5,"sp_work_OFF_RATING_RANK":5,"E_DEF_RATING_RANK":15,"DEF_RATING_RANK":17,"sp_work_DEF_RATING_RANK":17,"E_NET_RATING_RANK":7,"NET_RATING_RANK":12,"sp_work_NET_RATING_RANK":12,"AST_PCT_RANK":1,"AST_TO_RANK":7,"AST_RATIO_RANK":7,"OREB_PCT_RANK":14,"DREB_PCT_RANK":14,"REB_PCT_RANK":14,"TM_TOV_PCT_RANK":13,"E_TOV_PCT_RANK":13,"EFG_PCT_RANK":4,"TS_PCT_RANK":3,"USG_PCT_RANK":1,"E_USG_PCT_RANK":1,"E_PACE_RANK":3,"PACE_RANK":3,"sp_work_PACE_RANK":3,"PIE_RANK":2,"FGM_RANK":1,"FGA_RANK":1,"FGM_PG_RANK":1,"FGA_PG_RANK":1,"FG_PCT_RANK":5},"11":{"GROUP_SET":"Players","PLAYER_ID":2575,"PLAYER_NAME":"Luke Walton","GP":50,"W":16,"L":34,"W_PCT":0.32,"MIN":17.1,"E_OFF_RATING":102.7,"OFF_RATING":102.5,"sp_work_OFF_RATING":102.5,"E_DEF_RATING":105.6,"DEF_RATING":105,"sp_work_DEF_RATING":105,"E_NET_RATING":-2.9,"NET_RATING":-2.5,"sp_work_NET_RATING":-2.5,"AST_PCT":0.286,"AST_TO":2.77,"AST_RATIO":39.9,"OREB_PCT":0.045,"DREB_PCT":0.135,"REB_PCT":0.089,"TM_TOV_PCT":14.4,"E_TOV_PCT":14.4,"EFG_PCT":0.448,"TS_PCT":0.453,"USG_PCT":0.131,"E_USG_PCT":0.134,"E_PACE":94.02,"PACE":94.36,"PACE_PER40":78.63,"sp_work_PACE":94.36,"PIE":0.081,"POSS":1679,"FGM":71,"FGA":181,"FGM_PG":1.4,"FGA_PG":3.6,"FG_PCT":0.392,"GP_RANK":7,"W_RANK":8,"L_RANK":12,"W_PCT_RANK":6,"MIN_RANK":13,"E_OFF_RATING_RANK":5,"OFF_RATING_RANK":9,"sp_work_OFF_RATING_RANK":9,"E_DEF_RATING_RANK":9,"DEF_RATING_RANK":7,"sp_work_DEF_RATING_RANK":7,"E_NET_RATING_RANK":5,"NET_RATING_RANK":4,"sp_work_NET_RATING_RANK":4,"AST_PCT_RANK":2,"AST_TO_RANK":3,"AST_RATIO_RANK":1,"OREB_PCT_RANK":8,"DREB_PCT_RANK":6,"REB_PCT_RANK":7,"TM_TOV_PCT_RANK":18,"E_TOV_PCT_RANK":18,"EFG_PCT_RANK":13,"TS_PCT_RANK":15,"USG_PCT_RANK":18,"E_USG_PCT_RANK":18,"E_PACE_RANK":16,"PACE_RANK":8,"sp_work_PACE_RANK":8,"PIE_RANK":11,"FGM_RANK":13,"FGA_RANK":13,"FGM_PG_RANK":14,"FGA_PG_RANK":15,"FG_PCT_RANK":14},"12":{"GROUP_SET":"Players","PLAYER_ID":201578,"PLAYER_NAME":"Marreese Speights","GP":39,"W":13,"L":26,"W_PCT":0.333,"MIN":18.5,"E_OFF_RATING":101.1,"OFF_RATING":100.9,"sp_work_OFF_RATING":100.9,"E_DEF_RATING":107.3,"DEF_RATING":107.3,"sp_work_DEF_RATING":107.3,"E_NET_RATING":-6.1,"NET_RATING":-6.4,"sp_work_NET_RATING":-6.4,"AST_PCT":0.074,"AST_TO":0.64,"AST_RATIO":6.3,"OREB_PCT":0.096,"DREB_PCT":0.196,"REB_PCT":0.143,"TM_TOV_PCT":9.7,"E_TOV_PCT":9.8,"EFG_PCT":0.458,"TS_PCT":0.515,"USG_PCT":0.264,"E_USG_PCT":0.268,"E_PACE":95.02,"PACE":95.1,"PACE_PER40":79.25,"sp_work_PACE":95.1,"PIE":0.109,"POSS":1426,"FGM":154,"FGA":337,"FGM_PG":3.9,"FGA_PG":8.6,"FG_PCT":0.457,"GP_RANK":11,"W_RANK":9,"L_RANK":8,"W_PCT_RANK":3,"MIN_RANK":11,"E_OFF_RATING_RANK":10,"OFF_RATING_RANK":12,"sp_work_OFF_RATING_RANK":12,"E_DEF_RATING_RANK":13,"DEF_RATING_RANK":11,"sp_work_DEF_RATING_RANK":11,"E_NET_RATING_RANK":9,"NET_RATING_RANK":15,"sp_work_NET_RATING_RANK":15,"AST_PCT_RANK":16,"AST_TO_RANK":19,"AST_RATIO_RANK":19,"OREB_PCT_RANK":4,"DREB_PCT_RANK":2,"REB_PCT_RANK":3,"TM_TOV_PCT_RANK":9,"E_TOV_PCT_RANK":9,"EFG_PCT_RANK":8,"TS_PCT_RANK":7,"USG_PCT_RANK":2,"E_USG_PCT_RANK":2,"E_PACE_RANK":8,"PACE_RANK":5,"sp_work_PACE_RANK":5,"PIE_RANK":3,"FGM_RANK":7,"FGA_RANK":7,"FGM_PG_RANK":5,"FGA_PG_RANK":8,"FG_PCT_RANK":4},"13":{"GROUP_SET":"Players","PLAYER_ID":201956,"PLAYER_NAME":"Omri Casspi","GP":43,"W":10,"L":33,"W_PCT":0.233,"MIN":11.7,"E_OFF_RATING":94.2,"OFF_RATING":95.4,"sp_work_OFF_RATING":95.4,"E_DEF_RATING":100.5,"DEF_RATING":98.7,"sp_work_DEF_RATING":98.7,"E_NET_RATING":-6.3,"NET_RATING":-3.2,"sp_work_NET_RATING":-3.2,"AST_PCT":0.093,"AST_TO":1.27,"AST_RATIO":12.2,"OREB_PCT":0.036,"DREB_PCT":0.193,"REB_PCT":0.109,"TM_TOV_PCT":9.6,"E_TOV_PCT":9.6,"EFG_PCT":0.472,"TS_PCT":0.486,"USG_PCT":0.177,"E_USG_PCT":0.179,"E_PACE":92.87,"PACE":93.1,"PACE_PER40":77.59,"sp_work_PACE":93.1,"PIE":0.1,"POSS":967,"FGM":63,"FGA":160,"FGM_PG":1.5,"FGA_PG":3.7,"FG_PCT":0.394,"GP_RANK":10,"W_RANK":12,"L_RANK":11,"W_PCT_RANK":13,"MIN_RANK":15,"E_OFF_RATING_RANK":16,"OFF_RATING_RANK":17,"sp_work_OFF_RATING_RANK":17,"E_DEF_RATING_RANK":2,"DEF_RATING_RANK":3,"sp_work_DEF_RATING_RANK":3,"E_NET_RATING_RANK":11,"NET_RATING_RANK":5,"sp_work_NET_RATING_RANK":5,"AST_PCT_RANK":12,"AST_TO_RANK":12,"AST_RATIO_RANK":12,"OREB_PCT_RANK":9,"DREB_PCT_RANK":4,"REB_PCT_RANK":5,"TM_TOV_PCT_RANK":8,"E_TOV_PCT_RANK":8,"EFG_PCT_RANK":7,"TS_PCT_RANK":10,"USG_PCT_RANK":8,"E_USG_PCT_RANK":9,"E_PACE_RANK":17,"PACE_RANK":17,"sp_work_PACE_RANK":17,"PIE_RANK":5,"FGM_RANK":14,"FGA_RANK":14,"FGM_PG_RANK":13,"FGA_PG_RANK":14,"FG_PCT_RANK":13},"14":{"GROUP_SET":"Players","PLAYER_ID":202396,"PLAYER_NAME":"Samardo Samuels","GP":18,"W":3,"L":15,"W_PCT":0.167,"MIN":10.9,"E_OFF_RATING":95.3,"OFF_RATING":96.7,"sp_work_OFF_RATING":96.7,"E_DEF_RATING":104.8,"DEF_RATING":102.5,"sp_work_DEF_RATING":102.5,"E_NET_RATING":-9.5,"NET_RATING":-5.8,"sp_work_NET_RATING":-5.8,"AST_PCT":0.069,"AST_TO":1.33,"AST_RATIO":9.3,"OREB_PCT":0.046,"DREB_PCT":0.107,"REB_PCT":0.073,"TM_TOV_PCT":7,"E_TOV_PCT":7.1,"EFG_PCT":0.367,"TS_PCT":0.411,"USG_PCT":0.172,"E_USG_PCT":0.172,"E_PACE":96.74,"PACE":97.08,"PACE_PER40":80.9,"sp_work_PACE":97.08,"PIE":0.016,"POSS":394,"FGM":22,"FGA":60,"FGM_PG":1.2,"FGA_PG":3.3,"FG_PCT":0.367,"GP_RANK":17,"W_RANK":16,"L_RANK":3,"W_PCT_RANK":15,"MIN_RANK":17,"E_OFF_RATING_RANK":14,"OFF_RATING_RANK":15,"sp_work_OFF_RATING_RANK":15,"E_DEF_RATING_RANK":6,"DEF_RATING_RANK":5,"sp_work_DEF_RATING_RANK":5,"E_NET_RATING_RANK":16,"NET_RATING_RANK":13,"sp_work_NET_RATING_RANK":13,"AST_PCT_RANK":17,"AST_TO_RANK":11,"AST_RATIO_RANK":16,"OREB_PCT_RANK":7,"DREB_PCT_RANK":10,"REB_PCT_RANK":9,"TM_TOV_PCT_RANK":2,"E_TOV_PCT_RANK":2,"EFG_PCT_RANK":17,"TS_PCT_RANK":17,"USG_PCT_RANK":11,"E_USG_PCT_RANK":12,"E_PACE_RANK":2,"PACE_RANK":2,"sp_work_PACE_RANK":2,"PIE_RANK":17,"FGM_RANK":17,"FGA_RANK":17,"FGM_PG_RANK":17,"FGA_PG_RANK":17,"FG_PCT_RANK":15},"15":{"GROUP_SET":"Players","PLAYER_ID":2733,"PLAYER_NAME":"Shaun Livingston","GP":49,"W":17,"L":32,"W_PCT":0.347,"MIN":23.2,"E_OFF_RATING":104.5,"OFF_RATING":105.1,"sp_work_OFF_RATING":105.1,"E_DEF_RATING":105.3,"DEF_RATING":106.1,"sp_work_DEF_RATING":106.1,"E_NET_RATING":-0.8,"NET_RATING":-1,"sp_work_NET_RATING":-1,"AST_PCT":0.236,"AST_TO":3,"AST_RATIO":32,"OREB_PCT":0.025,"DREB_PCT":0.085,"REB_PCT":0.054,"TM_TOV_PCT":10.7,"E_TOV_PCT":10.7,"EFG_PCT":0.507,"TS_PCT":0.559,"USG_PCT":0.146,"E_USG_PCT":0.149,"E_PACE":94.5,"PACE":93.84,"PACE_PER40":78.2,"sp_work_PACE":93.84,"PIE":0.095,"POSS":2220,"FGM":142,"FGA":280,"FGM_PG":2.9,"FGA_PG":5.7,"FG_PCT":0.507,"GP_RANK":8,"W_RANK":7,"L_RANK":10,"W_PCT_RANK":1,"MIN_RANK":8,"E_OFF_RATING_RANK":2,"OFF_RATING_RANK":4,"sp_work_OFF_RATING_RANK":4,"E_DEF_RATING_RANK":8,"DEF_RATING_RANK":9,"sp_work_DEF_RATING_RANK":9,"E_NET_RATING_RANK":3,"NET_RATING_RANK":3,"sp_work_NET_RATING_RANK":3,"AST_PCT_RANK":5,"AST_TO_RANK":1,"AST_RATIO_RANK":2,"OREB_PCT_RANK":11,"DREB_PCT_RANK":15,"REB_PCT_RANK":13,"TM_TOV_PCT_RANK":12,"E_TOV_PCT_RANK":12,"EFG_PCT_RANK":3,"TS_PCT_RANK":1,"USG_PCT_RANK":16,"E_USG_PCT_RANK":16,"E_PACE_RANK":13,"PACE_RANK":10,"sp_work_PACE_RANK":10,"PIE_RANK":7,"FGM_RANK":9,"FGA_RANK":10,"FGM_PG_RANK":11,"FGA_PG_RANK":11,"FG_PCT_RANK":1},"16":{"GROUP_SET":"Players","PLAYER_ID":202684,"PLAYER_NAME":"Tristan Thompson","GP":82,"W":24,"L":58,"W_PCT":0.293,"MIN":31.3,"E_OFF_RATING":101.3,"OFF_RATING":103,"sp_work_OFF_RATING":103,"E_DEF_RATING":107,"DEF_RATING":107.6,"sp_work_DEF_RATING":107.6,"E_NET_RATING":-5.7,"NET_RATING":-4.6,"sp_work_NET_RATING":-4.6,"AST_PCT":0.069,"AST_TO":0.88,"AST_RATIO":9.3,"OREB_PCT":0.114,"DREB_PCT":0.196,"REB_PCT":0.153,"TM_TOV_PCT":10.6,"E_TOV_PCT":10.6,"EFG_PCT":0.488,"TS_PCT":0.516,"USG_PCT":0.181,"E_USG_PCT":0.183,"E_PACE":94.67,"PACE":93.61,"PACE_PER40":78.01,"sp_work_PACE":93.61,"PIE":0.102,"POSS":4999,"FGM":390,"FGA":799,"FGM_PG":4.8,"FGA_PG":9.7,"FG_PCT":0.488,"GP_RANK":1,"W_RANK":1,"L_RANK":18,"W_PCT_RANK":8,"MIN_RANK":3,"E_OFF_RATING_RANK":7,"OFF_RATING_RANK":7,"sp_work_OFF_RATING_RANK":7,"E_DEF_RATING_RANK":12,"DEF_RATING_RANK":14,"sp_work_DEF_RATING_RANK":14,"E_NET_RATING_RANK":8,"NET_RATING_RANK":11,"sp_work_NET_RATING_RANK":11,"AST_PCT_RANK":18,"AST_TO_RANK":18,"AST_RATIO_RANK":15,"OREB_PCT_RANK":2,"DREB_PCT_RANK":3,"REB_PCT_RANK":2,"TM_TOV_PCT_RANK":11,"E_TOV_PCT_RANK":11,"EFG_PCT_RANK":5,"TS_PCT_RANK":6,"USG_PCT_RANK":6,"E_USG_PCT_RANK":6,"E_PACE_RANK":11,"PACE_RANK":13,"sp_work_PACE_RANK":13,"PIE_RANK":4,"FGM_RANK":2,"FGA_RANK":3,"FGM_PG_RANK":4,"FGA_PG_RANK":4,"FG_PCT_RANK":2},"17":{"GROUP_SET":"Players","PLAYER_ID":203092,"PLAYER_NAME":"Tyler Zeller","GP":77,"W":24,"L":53,"W_PCT":0.312,"MIN":26.4,"E_OFF_RATING":99,"OFF_RATING":101.2,"sp_work_OFF_RATING":101.2,"E_DEF_RATING":106.9,"DEF_RATING":107.2,"sp_work_DEF_RATING":107.2,"E_NET_RATING":-8,"NET_RATING":-6,"sp_work_NET_RATING":-6,"AST_PCT":0.075,"AST_TO":1.01,"AST_RATIO":11.7,"OREB_PCT":0.074,"DREB_PCT":0.145,"REB_PCT":0.108,"TM_TOV_PCT":11.6,"E_TOV_PCT":11.6,"EFG_PCT":0.438,"TS_PCT":0.486,"USG_PCT":0.157,"E_USG_PCT":0.159,"E_PACE":94.75,"PACE":93.62,"PACE_PER40":78.02,"sp_work_PACE":93.62,"PIE":0.064,"POSS":3955,"FGM":245,"FGA":559,"FGM_PG":3.2,"FGA_PG":7.3,"FG_PCT":0.438,"GP_RANK":3,"W_RANK":1,"L_RANK":17,"W_PCT_RANK":7,"MIN_RANK":6,"E_OFF_RATING_RANK":12,"OFF_RATING_RANK":11,"sp_work_OFF_RATING_RANK":11,"E_DEF_RATING_RANK":11,"DEF_RATING_RANK":10,"sp_work_DEF_RATING_RANK":10,"E_NET_RATING_RANK":14,"NET_RATING_RANK":14,"sp_work_NET_RATING_RANK":14,"AST_PCT_RANK":15,"AST_TO_RANK":14,"AST_RATIO_RANK":14,"OREB_PCT_RANK":5,"DREB_PCT_RANK":5,"REB_PCT_RANK":6,"TM_TOV_PCT_RANK":14,"E_TOV_PCT_RANK":14,"EFG_PCT_RANK":14,"TS_PCT_RANK":11,"USG_PCT_RANK":14,"E_USG_PCT_RANK":14,"E_PACE_RANK":10,"PACE_RANK":11,"sp_work_PACE_RANK":11,"PIE_RANK":13,"FGM_RANK":6,"FGA_RANK":6,"FGM_PG_RANK":9,"FGA_PG_RANK":10,"FG_PCT_RANK":7},"18":{"GROUP_SET":"Players","PLAYER_ID":201961,"PLAYER_NAME":"Wayne Ellington","GP":38,"W":13,"L":25,"W_PCT":0.342,"MIN":25.9,"E_OFF_RATING":104.4,"OFF_RATING":105.3,"sp_work_OFF_RATING":105.3,"E_DEF_RATING":106.6,"DEF_RATING":108.6,"sp_work_DEF_RATING":108.6,"E_NET_RATING":-2.3,"NET_RATING":-3.3,"sp_work_NET_RATING":-3.3,"AST_PCT":0.099,"AST_TO":1.88,"AST_RATIO":13.8,"OREB_PCT":0.02,"DREB_PCT":0.098,"REB_PCT":0.058,"TM_TOV_PCT":7.3,"E_TOV_PCT":7.3,"EFG_PCT":0.52,"TS_PCT":0.556,"USG_PCT":0.174,"E_USG_PCT":0.177,"E_PACE":95.61,"PACE":94.31,"PACE_PER40":78.59,"sp_work_PACE":94.31,"PIE":0.093,"POSS":1939,"FGM":145,"FGA":330,"FGM_PG":3.8,"FGA_PG":8.7,"FG_PCT":0.439,"GP_RANK":12,"W_RANK":9,"L_RANK":7,"W_PCT_RANK":2,"MIN_RANK":7,"E_OFF_RATING_RANK":3,"OFF_RATING_RANK":3,"sp_work_OFF_RATING_RANK":3,"E_DEF_RATING_RANK":10,"DEF_RATING_RANK":16,"sp_work_DEF_RATING_RANK":16,"E_NET_RATING_RANK":4,"NET_RATING_RANK":6,"sp_work_NET_RATING_RANK":6,"AST_PCT_RANK":10,"AST_TO_RANK":6,"AST_RATIO_RANK":10,"OREB_PCT_RANK":12,"DREB_PCT_RANK":13,"REB_PCT_RANK":12,"TM_TOV_PCT_RANK":3,"E_TOV_PCT_RANK":3,"EFG_PCT_RANK":1,"TS_PCT_RANK":2,"USG_PCT_RANK":10,"E_USG_PCT_RANK":10,"E_PACE_RANK":4,"PACE_RANK":9,"sp_work_PACE_RANK":9,"PIE_RANK":8,"FGM_RANK":8,"FGA_RANK":8,"FGM_PG_RANK":7,"FGA_PG_RANK":7,"FG_PCT_RANK":6}}}